javap : Error: class not found: C:\Users\sergi\AppData\Roaming\industrialis-launcher\instances\2.8.0\.minecraft\mods\GT
NewHorizonsCoreMod-2.7.260.jar!com.dreammaster.scripts.ScriptGadomancy
At line:1 char:1
+ javap -c -l "C:\Users\sergi\AppData\Roaming\industrialis-launcher\ins ...
+ ~~~~~~~~~~~~~~~~~~~~~~~~~~~~~~~~~~~~~~~~~~~~~~~~~~~~~~~~~~~~~~~~~~~~~
    + CategoryInfo          : NotSpecified: (Error: class no...ScriptGadomancy:String) [], RemoteException
    + FullyQualifiedErrorId : NativeCommandError
 

> Compiled from "ScriptGadomancy.java"
> public class com.dreammaster.scripts.ScriptGadomancy implements com.dreammaster.scripts.IScriptLoader {
>   public com.dreammaster.scripts.ScriptGadomancy();
      Code:
         0: aload_0
>           0       5     0  this   Lcom/dreammaster/scripts/ScriptGadomancy;
  
    public java.lang.String getScriptName();
>        0: ldc           #17                 // String Gadomancy
         2: areturn
      LineNumberTable:
>           0       3     0  this   Lcom/dreammaster/scripts/ScriptGadomancy;
  
    public java.util.List<java.lang.String> getDependencies();
>        6: getstatic     #27                 // Field gregtech/api/enums/Mods.Gadomancy:Lgregtech/api/enums/Mods;
         9: getfield      #31                 // Field gregtech/api/enums/Mods.ID:Ljava/lang/String;
        12: aastore
>           0      35     0  this   Lcom/dreammaster/scripts/ScriptGadomancy;
  
>   public void loadRecipes();
      Code:
         0: aload_0
>        7: ldc           #46                 // String blockCosmeticSlabStone
>        9: ldc2_w        #47                 // long 2l
        12: iconst_1
        13: getstatic     #52                 // Field missing:Lnet/minecraft/item/ItemStack;
>       31: ldc           #60                 // String blockCosmeticSolid
        33: lconst_1
        34: bipush        11
>       45: ldc           #62                 // String craftingToolSaw
        47: aastore
        48: invokevirtual #66                 // Method 
addShapelessRecipe:(Lnet/minecraft/item/ItemStack;[Ljava/lang/Object;)Z
>       59: ldc           #68                 // String blockStairsEldritch
>       61: ldc2_w        #69                 // long 4l
        64: iconst_0
        65: getstatic     #52                 // Field missing:Lnet/minecraft/item/ItemStack;
>       84: ldc           #60                 // String blockCosmeticSolid
        86: lconst_1
        87: bipush        11
>      112: ldc           #60                 // String blockCosmeticSolid
       114: lconst_1
       115: bipush        11
>      132: ldc           #60                 // String blockCosmeticSolid
       134: lconst_1
       135: bipush        11
>      157: ldc           #60                 // String blockCosmeticSolid
       159: lconst_1
       160: bipush        11
>      178: ldc           #60                 // String blockCosmeticSolid
       180: lconst_1
       181: bipush        11
>      199: ldc           #60                 // String blockCosmeticSolid
       201: lconst_1
       202: bipush        11
>      235: ldc           #60                 // String blockCosmeticSolid
       237: lconst_1
       238: bipush        11
>      262: ldc           #46                 // String blockCosmeticSlabStone
>      264: ldc2_w        #69                 // long 4l
       267: iconst_1
       268: getstatic     #52                 // Field missing:Lnet/minecraft/item/ItemStack;
>      284: ldc           #100                // String water
       286: bipush        32
       288: invokestatic  #106                // Method 
net/minecraftforge/fluids/FluidRegistry.getFluidStack:(Ljava/lang/String;I)Lnet/minecraftforge/fluids/FluidStack;
>      333: ldc           #60                 // String blockCosmeticSolid
       335: lconst_1
       336: bipush        11
>      360: ldc           #46                 // String blockCosmeticSlabStone
>      362: ldc2_w        #69                 // long 4l
       365: iconst_1
       366: getstatic     #52                 // Field missing:Lnet/minecraft/item/ItemStack;
>      382: ldc           #129                // String ic2distilledwater
       384: bipush        20
       386: invokestatic  #106                // Method 
net/minecraftforge/fluids/FluidRegistry.getFluidStack:(Ljava/lang/String;I)Lnet/minecraftforge/fluids/FluidStack;
>      431: ldc           #60                 // String blockCosmeticSolid
       433: lconst_1
       434: bipush        11
>      458: ldc           #46                 // String blockCosmeticSlabStone
>      460: ldc2_w        #69                 // long 4l
       463: iconst_1
       464: getstatic     #52                 // Field missing:Lnet/minecraft/item/ItemStack;
>      480: ldc           #131                // String lubricant
       482: bipush        8
       484: invokestatic  #106                // Method 
net/minecraftforge/fluids/FluidRegistry.getFluidStack:(Ljava/lang/String;I)Lnet/minecraftforge/fluids/FluidStack;
>      509: getstatic     #27                 // Field gregtech/api/enums/Mods.Gadomancy:Lgregtech/api/enums/Mods;
       512: getfield      #31                 // Field gregtech/api/enums/Mods.ID:Ljava/lang/String;
>      515: ldc           #133                // String itemSilverwoodGolemPlacer
       517: lconst_1
       518: bipush        8
>      530: getstatic     #27                 // Field gregtech/api/enums/Mods.Gadomancy:Lgregtech/api/enums/Mods;
       533: getfield      #31                 // Field gregtech/api/enums/Mods.ID:Ljava/lang/String;
>      536: ldc           #133                // String itemSilverwoodGolemPlacer
       538: lconst_1
       539: bipush        8
>      541: ldc           #141                // String {gadomancy:{upgrades:{runicShield:1b}}}
       543: getstatic     #52                 // Field missing:Lnet/minecraft/item/ItemStack;
       546: invokevirtual #145                // Method createItemStack:(Ljava/lang/String;Ljava/lang/String;JILjava/la
ng/String;Lnet/minecraft/item/ItemStack;)Lnet/minecraft/item/ItemStack;
>      552: getstatic     #27                 // Field gregtech/api/enums/Mods.Gadomancy:Lgregtech/api/enums/Mods;
       555: getfield      #31                 // Field gregtech/api/enums/Mods.ID:Ljava/lang/String;
>      558: ldc           #147                // String ItemGolemCoreBreak
       560: lconst_1
       561: iconst_0
>      571: getstatic     #27                 // Field gregtech/api/enums/Mods.Gadomancy:Lgregtech/api/enums/Mods;
       574: getfield      #31                 // Field gregtech/api/enums/Mods.ID:Ljava/lang/String;
>      577: ldc           #147                // String ItemGolemCoreBreak
       579: lconst_1
       580: iconst_1
>      596: ldc           #60                 // String blockCosmeticSolid
>      598: ldc2_w        #69                 // long 4l
       601: bipush        11
       603: getstatic     #52                 // Field missing:Lnet/minecraft/item/ItemStack;
>      618: ldc           #60                 // String blockCosmeticSolid
       620: lconst_1
       621: bipush        15
>      632: getstatic     #27                 // Field gregtech/api/enums/Mods.Gadomancy:Lgregtech/api/enums/Mods;
       635: getfield      #31                 // Field gregtech/api/enums/Mods.ID:Ljava/lang/String;
>      638: ldc           #155                // String BlockNodeManipulator
       640: lconst_1
       641: iconst_5
>      651: getstatic     #27                 // Field gregtech/api/enums/Mods.Gadomancy:Lgregtech/api/enums/Mods;
       654: getfield      #31                 // Field gregtech/api/enums/Mods.ID:Ljava/lang/String;
>      657: ldc           #157                // String BlockStoneMachine
       659: lconst_1
       660: iconst_0
>      670: getstatic     #27                 // Field gregtech/api/enums/Mods.Gadomancy:Lgregtech/api/enums/Mods;
       673: getfield      #31                 // Field gregtech/api/enums/Mods.ID:Ljava/lang/String;
>      676: ldc           #159                // String BlockInfusionClaw
       678: lconst_1
       679: iconst_0
>      689: getstatic     #27                 // Field gregtech/api/enums/Mods.Gadomancy:Lgregtech/api/enums/Mods;
       692: getfield      #31                 // Field gregtech/api/enums/Mods.ID:Ljava/lang/String;
>      695: ldc           #161                // String BlockRemoteJar
       697: lconst_1
       698: iconst_0
>      708: getstatic     #27                 // Field gregtech/api/enums/Mods.Gadomancy:Lgregtech/api/enums/Mods;
       711: getfield      #31                 // Field gregtech/api/enums/Mods.ID:Ljava/lang/String;
>      714: ldc           #163                // String BlockArcaneDropper
       716: lconst_1
       717: iconst_0
>      727: getstatic     #27                 // Field gregtech/api/enums/Mods.Gadomancy:Lgregtech/api/enums/Mods;
       730: getfield      #31                 // Field gregtech/api/enums/Mods.ID:Ljava/lang/String;
>      733: ldc           #157                // String BlockStoneMachine
       735: lconst_1
       736: iconst_2
>      746: getstatic     #27                 // Field gregtech/api/enums/Mods.Gadomancy:Lgregtech/api/enums/Mods;
       749: getfield      #31                 // Field gregtech/api/enums/Mods.ID:Ljava/lang/String;
>      752: ldc           #157                // String BlockStoneMachine
       754: lconst_1
       755: iconst_2
>      765: getstatic     #27                 // Field gregtech/api/enums/Mods.Gadomancy:Lgregtech/api/enums/Mods;
       768: getfield      #31                 // Field gregtech/api/enums/Mods.ID:Ljava/lang/String;
>      771: ldc           #157                // String BlockStoneMachine
       773: lconst_1
       774: iconst_2
>      784: getstatic     #27                 // Field gregtech/api/enums/Mods.Gadomancy:Lgregtech/api/enums/Mods;
       787: getfield      #31                 // Field gregtech/api/enums/Mods.ID:Ljava/lang/String;
>      790: ldc           #157                // String BlockStoneMachine
       792: lconst_1
       793: iconst_2
>      803: getstatic     #27                 // Field gregtech/api/enums/Mods.Gadomancy:Lgregtech/api/enums/Mods;
       806: getfield      #31                 // Field gregtech/api/enums/Mods.ID:Ljava/lang/String;
>      809: ldc           #157                // String BlockStoneMachine
       811: lconst_1
       812: iconst_1
>      822: getstatic     #27                 // Field gregtech/api/enums/Mods.Gadomancy:Lgregtech/api/enums/Mods;
       825: getfield      #31                 // Field gregtech/api/enums/Mods.ID:Ljava/lang/String;
>      828: ldc           #157                // String BlockStoneMachine
       830: lconst_1
       831: iconst_3
>      841: getstatic     #27                 // Field gregtech/api/enums/Mods.Gadomancy:Lgregtech/api/enums/Mods;
       844: getfield      #31                 // Field gregtech/api/enums/Mods.ID:Ljava/lang/String;
>      847: ldc           #157                // String BlockStoneMachine
       849: lconst_1
       850: iconst_4
>      860: getstatic     #27                 // Field gregtech/api/enums/Mods.Gadomancy:Lgregtech/api/enums/Mods;
       863: getfield      #31                 // Field gregtech/api/enums/Mods.ID:Ljava/lang/String;
>      866: ldc           #165                // String BlockAuraPylon
       868: lconst_1
       869: iconst_0
>      879: getstatic     #27                 // Field gregtech/api/enums/Mods.Gadomancy:Lgregtech/api/enums/Mods;
       882: getfield      #31                 // Field gregtech/api/enums/Mods.ID:Ljava/lang/String;
>      885: ldc           #165                // String BlockAuraPylon
       887: lconst_1
       888: iconst_1
>      898: getstatic     #27                 // Field gregtech/api/enums/Mods.Gadomancy:Lgregtech/api/enums/Mods;
       901: getfield      #31                 // Field gregtech/api/enums/Mods.ID:Ljava/lang/String;
>      904: ldc           #167                // String BlockKnowledgeBook
       906: lconst_1
       907: iconst_0
>      917: getstatic     #27                 // Field gregtech/api/enums/Mods.Gadomancy:Lgregtech/api/enums/Mods;
       920: getfield      #31                 // Field gregtech/api/enums/Mods.ID:Ljava/lang/String;
>      923: ldc           #169                // String BlockEssentiaCompressor
>      925: ldc2_w        #170                // long 3l
       928: iconst_0
       929: getstatic     #52                 // Field missing:Lnet/minecraft/item/ItemStack;
>      938: ldc           #173                // String GADOMANCY.GOLEMSILVERWOOD
>      940: getstatic     #27                 // Field gregtech/api/enums/Mods.Gadomancy:Lgregtech/api/enums/Mods;
       943: getfield      #31                 // Field gregtech/api/enums/Mods.ID:Ljava/lang/String;
>      946: ldc           #133                // String itemSilverwoodGolemPlacer
       948: lconst_1
       949: bipush        8
>      966: ldc           #178                // String humanus
       968: invokestatic  #184                // Method 
thaumcraft/api/aspects/Aspect.getAspect:(Ljava/lang/String;)Lthaumcraft/api/aspects/Aspect;
       971: bipush        16
>      976: ldc           #190                // String motus
       978: invokestatic  #184                // Method 
thaumcraft/api/aspects/Aspect.getAspect:(Ljava/lang/String;)Lthaumcraft/api/aspects/Aspect;
       981: bipush        16
>      986: ldc           #192                // String praecantatio
       988: invokestatic  #184                // Method 
thaumcraft/api/aspects/Aspect.getAspect:(Ljava/lang/String;)Lthaumcraft/api/aspects/Aspect;
       991: bipush        32
>      996: ldc           #194                // String sensus
       998: invokestatic  #184                // Method 
thaumcraft/api/aspects/Aspect.getAspect:(Ljava/lang/String;)Lthaumcraft/api/aspects/Aspect;
      1001: bipush        16
>     1006: ldc           #196                // String cognitio
      1008: invokestatic  #184                // Method 
thaumcraft/api/aspects/Aspect.getAspect:(Ljava/lang/String;)Lthaumcraft/api/aspects/Aspect;
      1011: bipush        8
>     1016: ldc           #198                // String ordo
      1018: invokestatic  #184                // Method 
thaumcraft/api/aspects/Aspect.getAspect:(Ljava/lang/String;)Lthaumcraft/api/aspects/Aspect;
      1021: bipush        32
>     1032: ldc           #200                // String ItemGolemPlacer
      1034: lconst_1
      1035: iconst_1
>     1055: ldc           #202                // String ItemZombieBrain
      1057: lconst_1
      1058: iconst_0
>     1074: ldc           #204                // String blockMagicalLog
      1076: lconst_1
      1077: iconst_1
>     1093: ldc           #206                // String ItemResource
      1095: lconst_1
      1096: bipush        14
>     1113: ldc           #206                // String ItemResource
      1115: lconst_1
      1116: iconst_3
>     1132: ldc           #206                // String ItemResource
      1134: lconst_1
      1135: bipush        9
>     1152: ldc           #206                // String ItemResource
      1154: lconst_1
      1155: bipush        15
>     1173: ldc           #206                // String ItemResource
      1175: lconst_1
      1176: bipush        9
>     1194: ldc           #206                // String ItemResource
      1196: lconst_1
      1197: iconst_3
>     1214: ldc           #206                // String ItemResource
      1216: lconst_1
      1217: bipush        14
>     1235: ldc           #204                // String blockMagicalLog
      1237: lconst_1
      1238: iconst_1
>     1250: ldc           #173                // String GADOMANCY.GOLEMSILVERWOOD
      1252: new           #175                // class thaumcraft/api/aspects/AspectList
      1255: dup
>     1259: ldc           #196                // String cognitio
      1261: invokestatic  #184                // Method 
thaumcraft/api/aspects/Aspect.getAspect:(Ljava/lang/String;)Lthaumcraft/api/aspects/Aspect;
      1264: bipush        21
>     1269: ldc           #190                // String motus
      1271: invokestatic  #184                // Method 
thaumcraft/api/aspects/Aspect.getAspect:(Ljava/lang/String;)Lthaumcraft/api/aspects/Aspect;
      1274: bipush        18
>     1279: ldc           #212                // String arbor
      1281: invokestatic  #184                // Method 
thaumcraft/api/aspects/Aspect.getAspect:(Ljava/lang/String;)Lthaumcraft/api/aspects/Aspect;
      1284: bipush        15
>     1289: ldc           #192                // String praecantatio
      1291: invokestatic  #184                // Method 
thaumcraft/api/aspects/Aspect.getAspect:(Ljava/lang/String;)Lthaumcraft/api/aspects/Aspect;
      1294: bipush        12
>     1299: ldc           #198                // String ordo
      1301: invokestatic  #184                // Method 
thaumcraft/api/aspects/Aspect.getAspect:(Ljava/lang/String;)Lthaumcraft/api/aspects/Aspect;
      1304: bipush        9
>     1309: ldc           #214                // String corpus
      1311: invokestatic  #184                // Method 
thaumcraft/api/aspects/Aspect.getAspect:(Ljava/lang/String;)Lthaumcraft/api/aspects/Aspect;
      1314: bipush        6
>     1319: ldc           #216                // String permutatio
      1321: invokestatic  #184                // Method 
thaumcraft/api/aspects/Aspect.getAspect:(Ljava/lang/String;)Lthaumcraft/api/aspects/Aspect;
      1324: iconst_3
>     1328: invokestatic  #220                // Method 
com/dreammaster/thaumcraft/TCHelper.setResearchAspects:(Ljava/lang/String;Lthaumcraft/api/aspects/AspectList;)V
>     1331: ldc           #173                // String GADOMANCY.GOLEMSILVERWOOD
      1333: iconst_3
>     1334: invokestatic  #224                // Method 
com/dreammaster/thaumcraft/TCHelper.setResearchComplexity:(Ljava/lang/String;I)V
>     1337: ldc           #226                // String GADOMANCY.GOLEMCOREBREAK
>     1339: getstatic     #27                 // Field gregtech/api/enums/Mods.Gadomancy:Lgregtech/api/enums/Mods;
      1342: getfield      #31                 // Field gregtech/api/enums/Mods.ID:Ljava/lang/String;
>     1345: ldc           #147                // String ItemGolemCoreBreak
      1347: lconst_1
      1348: iconst_0
>     1364: ldc           #228                // String instrumentum
      1366: invokestatic  #184                // Method 
thaumcraft/api/aspects/Aspect.getAspect:(Ljava/lang/String;)Lthaumcraft/api/aspects/Aspect;
      1369: bipush        32
>     1374: ldc           #230                // String perditio
      1376: invokestatic  #184                // Method 
thaumcraft/api/aspects/Aspect.getAspect:(Ljava/lang/String;)Lthaumcraft/api/aspects/Aspect;
      1379: bipush        16
>     1384: ldc           #232                // String machina
      1386: invokestatic  #184                // Method 
thaumcraft/api/aspects/Aspect.getAspect:(Ljava/lang/String;)Lthaumcraft/api/aspects/Aspect;
      1389: bipush        24
>     1394: ldc           #192                // String praecantatio
      1396: invokestatic  #184                // Method 
thaumcraft/api/aspects/Aspect.getAspect:(Ljava/lang/String;)Lthaumcraft/api/aspects/Aspect;
      1399: bipush        8
>     1404: ldc           #234                // String perfodio
      1406: invokestatic  #184                // Method 
thaumcraft/api/aspects/Aspect.getAspect:(Ljava/lang/String;)Lthaumcraft/api/aspects/Aspect;
      1409: bipush        8
>     1420: ldc           #236                // String ItemGolemCore
      1422: lconst_1
      1423: iconst_3
>     1443: ldc           #238                // String ItemPickaxeElemental
      1445: lconst_1
      1446: iconst_0
>     1462: ldc           #240                // String blockCrystal
      1464: lconst_1
      1465: iconst_0
>     1481: ldc           #240                // String blockCrystal
      1483: lconst_1
      1484: iconst_1
>     1500: ldc           #242                // String ItemAxeElemental
      1502: lconst_1
      1503: iconst_0
>     1519: ldc           #240                // String blockCrystal
      1521: lconst_1
      1522: iconst_2
>     1538: ldc           #240                // String blockCrystal
      1540: lconst_1
      1541: iconst_3
>     1558: ldc           #244                // String ItemShovelElemental
      1560: lconst_1
      1561: iconst_0
>     1578: ldc           #240                // String blockCrystal
      1580: lconst_1
      1581: iconst_4
>     1598: ldc           #240                // String blockCrystal
      1600: lconst_1
      1601: iconst_5
>     1613: ldc           #226                // String GADOMANCY.GOLEMCOREBREAK
      1615: new           #175                // class thaumcraft/api/aspects/AspectList
      1618: dup
>     1622: ldc           #228                // String instrumentum
      1624: invokestatic  #184                // Method 
thaumcraft/api/aspects/Aspect.getAspect:(Ljava/lang/String;)Lthaumcraft/api/aspects/Aspect;
      1627: bipush        15
>     1632: ldc           #230                // String perditio
      1634: invokestatic  #184                // Method 
thaumcraft/api/aspects/Aspect.getAspect:(Ljava/lang/String;)Lthaumcraft/api/aspects/Aspect;
      1637: bipush        12
>     1642: ldc           #232                // String machina
      1644: invokestatic  #184                // Method 
thaumcraft/api/aspects/Aspect.getAspect:(Ljava/lang/String;)Lthaumcraft/api/aspects/Aspect;
      1647: bipush        9
>     1652: ldc           #192                // String praecantatio
      1654: invokestatic  #184                // Method 
thaumcraft/api/aspects/Aspect.getAspect:(Ljava/lang/String;)Lthaumcraft/api/aspects/Aspect;
      1657: bipush        6
>     1662: ldc           #234                // String perfodio
      1664: invokestatic  #184                // Method 
thaumcraft/api/aspects/Aspect.getAspect:(Ljava/lang/String;)Lthaumcraft/api/aspects/Aspect;
      1667: iconst_3
>     1671: invokestatic  #220                // Method 
com/dreammaster/thaumcraft/TCHelper.setResearchAspects:(Ljava/lang/String;Lthaumcraft/api/aspects/AspectList;)V
>     1674: ldc           #226                // String GADOMANCY.GOLEMCOREBREAK
      1676: iconst_3
>     1677: invokestatic  #224                // Method 
com/dreammaster/thaumcraft/TCHelper.setResearchComplexity:(Ljava/lang/String;I)V
>     1680: ldc           #246                // String GADOMANCY.GOLEMCOREBODYGUARD
>     1682: getstatic     #27                 // Field gregtech/api/enums/Mods.Gadomancy:Lgregtech/api/enums/Mods;
      1685: getfield      #31                 // Field gregtech/api/enums/Mods.ID:Ljava/lang/String;
>     1688: ldc           #147                // String ItemGolemCoreBreak
      1690: lconst_1
      1691: iconst_1
>     1707: ldc           #228                // String instrumentum
      1709: invokestatic  #184                // Method 
thaumcraft/api/aspects/Aspect.getAspect:(Ljava/lang/String;)Lthaumcraft/api/aspects/Aspect;
      1712: bipush        32
>     1717: ldc           #232                // String machina
      1719: invokestatic  #184                // Method 
thaumcraft/api/aspects/Aspect.getAspect:(Ljava/lang/String;)Lthaumcraft/api/aspects/Aspect;
      1722: bipush        24
>     1727: ldc           #248                // String telum
      1729: invokestatic  #184                // Method 
thaumcraft/api/aspects/Aspect.getAspect:(Ljava/lang/String;)Lthaumcraft/api/aspects/Aspect;
      1732: bipush        16
>     1737: ldc           #250                // String tutamen
      1739: invokestatic  #184                // Method 
thaumcraft/api/aspects/Aspect.getAspect:(Ljava/lang/String;)Lthaumcraft/api/aspects/Aspect;
      1742: bipush        24
>     1747: ldc           #198                // String ordo
      1749: invokestatic  #184                // Method 
thaumcraft/api/aspects/Aspect.getAspect:(Ljava/lang/String;)Lthaumcraft/api/aspects/Aspect;
      1752: bipush        8
>     1757: ldc           #252                // String auram
      1759: invokestatic  #184                // Method 
thaumcraft/api/aspects/Aspect.getAspect:(Ljava/lang/String;)Lthaumcraft/api/aspects/Aspect;
      1762: bipush        8
>     1773: ldc           #236                // String ItemGolemCore
      1775: lconst_1
      1776: iconst_4
>     1796: ldc           #254                // String ItemSwordElemental
      1798: lconst_1
      1799: iconst_0
>     1815: ldc_w         #256                // String ItemHelmetThaumium
      1818: lconst_1
      1819: iconst_0
>     1849: ldc_w         #268                // String ItemChestplateThaumium
      1852: lconst_1
      1853: iconst_0
>     1869: ldc_w         #270                // String BootsTraveller
      1872: lconst_1
      1873: iconst_0
>     1889: ldc_w         #272                // String ItemLeggingsThaumium
      1892: lconst_1
      1893: iconst_0
>     1925: ldc           #240                // String blockCrystal
      1927: lconst_1
      1928: bipush        6
>     1941: ldc           #246                // String GADOMANCY.GOLEMCOREBODYGUARD
      1943: new           #175                // class thaumcraft/api/aspects/AspectList
      1946: dup
>     1950: ldc           #228                // String instrumentum
      1952: invokestatic  #184                // Method 
thaumcraft/api/aspects/Aspect.getAspect:(Ljava/lang/String;)Lthaumcraft/api/aspects/Aspect;
      1955: bipush        18
>     1960: ldc           #198                // String ordo
      1962: invokestatic  #184                // Method 
thaumcraft/api/aspects/Aspect.getAspect:(Ljava/lang/String;)Lthaumcraft/api/aspects/Aspect;
      1965: bipush        15
>     1970: ldc           #232                // String machina
      1972: invokestatic  #184                // Method 
thaumcraft/api/aspects/Aspect.getAspect:(Ljava/lang/String;)Lthaumcraft/api/aspects/Aspect;
      1975: bipush        12
>     1980: ldc           #248                // String telum
      1982: invokestatic  #184                // Method 
thaumcraft/api/aspects/Aspect.getAspect:(Ljava/lang/String;)Lthaumcraft/api/aspects/Aspect;
      1985: bipush        9
>     1990: ldc           #250                // String tutamen
      1992: invokestatic  #184                // Method 
thaumcraft/api/aspects/Aspect.getAspect:(Ljava/lang/String;)Lthaumcraft/api/aspects/Aspect;
      1995: bipush        6
>     2000: ldc           #252                // String auram
      2002: invokestatic  #184                // Method 
thaumcraft/api/aspects/Aspect.getAspect:(Ljava/lang/String;)Lthaumcraft/api/aspects/Aspect;
      2005: iconst_3
>     2009: invokestatic  #220                // Method 
com/dreammaster/thaumcraft/TCHelper.setResearchAspects:(Ljava/lang/String;Lthaumcraft/api/aspects/AspectList;)V
>     2012: ldc           #246                // String GADOMANCY.GOLEMCOREBODYGUARD
      2014: iconst_3
>     2015: invokestatic  #224                // Method 
com/dreammaster/thaumcraft/TCHelper.setResearchComplexity:(Ljava/lang/String;I)V
>     2018: ldc_w         #274                // String GADOMANCY.GOLEMRUNICSHIELD
      2021: new           #175                // class thaumcraft/api/aspects/AspectList
      2024: dup
>     2028: ldc           #252                // String auram
      2030: invokestatic  #184                // Method 
thaumcraft/api/aspects/Aspect.getAspect:(Ljava/lang/String;)Lthaumcraft/api/aspects/Aspect;
      2033: bipush        15
>     2038: ldc           #190                // String motus
      2040: invokestatic  #184                // Method 
thaumcraft/api/aspects/Aspect.getAspect:(Ljava/lang/String;)Lthaumcraft/api/aspects/Aspect;
      2043: bipush        12
>     2048: ldc           #250                // String tutamen
      2050: invokestatic  #184                // Method 
thaumcraft/api/aspects/Aspect.getAspect:(Ljava/lang/String;)Lthaumcraft/api/aspects/Aspect;
      2053: bipush        9
>     2058: ldc           #192                // String praecantatio
      2060: invokestatic  #184                // Method 
thaumcraft/api/aspects/Aspect.getAspect:(Ljava/lang/String;)Lthaumcraft/api/aspects/Aspect;
      2063: bipush        6
>     2068: ldc           #198                // String ordo
      2070: invokestatic  #184                // Method 
thaumcraft/api/aspects/Aspect.getAspect:(Ljava/lang/String;)Lthaumcraft/api/aspects/Aspect;
      2073: iconst_3
>     2077: invokestatic  #220                // Method 
com/dreammaster/thaumcraft/TCHelper.setResearchAspects:(Ljava/lang/String;Lthaumcraft/api/aspects/AspectList;)V
>     2080: ldc_w         #274                // String GADOMANCY.GOLEMRUNICSHIELD
      2083: iconst_3
>     2084: invokestatic  #224                // Method 
com/dreammaster/thaumcraft/TCHelper.setResearchComplexity:(Ljava/lang/String;I)V
>     2087: ldc_w         #276                // String GADOMANCY.ANCIENT_STONES
      2090: getstatic     #34                 // Field gregtech/api/enums/Mods.Thaumcraft:Lgregtech/api/enums/Mods;
      2093: getfield      #31                 // Field gregtech/api/enums/Mods.ID:Ljava/lang/String;
>     2096: ldc           #60                 // String blockCosmeticSolid
>     2098: ldc2_w        #277                // long 6l
      2101: bipush        11
      2103: getstatic     #52                 // Field missing:Lnet/minecraft/item/ItemStack;
>     2116: ldc_w         #280                // String terra
      2119: invokestatic  #184                // Method 
thaumcraft/api/aspects/Aspect.getAspect:(Ljava/lang/String;)Lthaumcraft/api/aspects/Aspect;
      2122: bipush        6
>     2127: ldc           #230                // String perditio
      2129: invokestatic  #184                // Method 
thaumcraft/api/aspects/Aspect.getAspect:(Ljava/lang/String;)Lthaumcraft/api/aspects/Aspect;
      2132: bipush        12
>     2137: ldc_w         #282                // String ignis
      2140: invokestatic  #184                // Method 
thaumcraft/api/aspects/Aspect.getAspect:(Ljava/lang/String;)Lthaumcraft/api/aspects/Aspect;
      2143: bipush        6
>     2155: ldc_w         #284                // String abc
      2158: aastore
      2159: dup
>     2161: ldc_w         #286                // String def
      2164: aastore
      2165: dup
>     2167: ldc_w         #288                // String ghi
      2170: aastore
      2171: dup
>     2187: ldc           #60                 // String blockCosmeticSolid
      2189: lconst_1
      2190: bipush        6
>     2216: ldc           #60                 // String blockCosmeticSolid
      2218: lconst_1
      2219: bipush        6
>     2246: ldc           #60                 // String blockCosmeticSolid
      2248: lconst_1
      2249: bipush        6
>     2276: ldc_w         #296                // String blockEldritch
      2279: lconst_1
      2280: iconst_4
>     2306: ldc_w         #298                // String ItemEldritchObject
      2309: lconst_1
      2310: iconst_0
>     2336: ldc_w         #296                // String blockEldritch
      2339: lconst_1
      2340: iconst_4
>     2366: ldc           #60                 // String blockCosmeticSolid
      2368: lconst_1
      2369: bipush        6
>     2396: ldc           #60                 // String blockCosmeticSolid
      2398: lconst_1
      2399: bipush        6
>     2426: ldc           #60                 // String blockCosmeticSolid
      2428: lconst_1
      2429: bipush        6
>     2442: ldc_w         #276                // String GADOMANCY.ANCIENT_STONES
      2445: new           #175                // class thaumcraft/api/aspects/AspectList
      2448: dup
>     2452: ldc_w         #282                // String ignis
      2455: invokestatic  #184                // Method 
thaumcraft/api/aspects/Aspect.getAspect:(Ljava/lang/String;)Lthaumcraft/api/aspects/Aspect;
      2458: bipush        15
>     2463: ldc_w         #306                // String alienis
      2466: invokestatic  #184                // Method 
thaumcraft/api/aspects/Aspect.getAspect:(Ljava/lang/String;)Lthaumcraft/api/aspects/Aspect;
      2469: bipush        12
>     2474: ldc           #230                // String perditio
      2476: invokestatic  #184                // Method 
thaumcraft/api/aspects/Aspect.getAspect:(Ljava/lang/String;)Lthaumcraft/api/aspects/Aspect;
      2479: bipush        9
>     2484: ldc_w         #280                // String terra
      2487: invokestatic  #184                // Method 
thaumcraft/api/aspects/Aspect.getAspect:(Ljava/lang/String;)Lthaumcraft/api/aspects/Aspect;
      2490: bipush        6
>     2495: ldc           #216                // String permutatio
      2497: invokestatic  #184                // Method 
thaumcraft/api/aspects/Aspect.getAspect:(Ljava/lang/String;)Lthaumcraft/api/aspects/Aspect;
      2500: iconst_3
>     2504: invokestatic  #220                // Method 
com/dreammaster/thaumcraft/TCHelper.setResearchAspects:(Ljava/lang/String;Lthaumcraft/api/aspects/AspectList;)V
>     2507: ldc_w         #276                // String GADOMANCY.ANCIENT_STONES
      2510: iconst_3
>     2511: invokestatic  #224                // Method 
com/dreammaster/thaumcraft/TCHelper.setResearchComplexity:(Ljava/lang/String;I)V
>     2514: ldc_w         #276                // String GADOMANCY.ANCIENT_STONES
      2517: getstatic     #34                 // Field gregtech/api/enums/Mods.Thaumcraft:Lgregtech/api/enums/Mods;
      2520: getfield      #31                 // Field gregtech/api/enums/Mods.ID:Ljava/lang/String;
>     2523: ldc           #60                 // String blockCosmeticSolid
      2525: lconst_1
      2526: bipush        15
>     2540: ldc           #60                 // String blockCosmeticSolid
      2542: lconst_1
      2543: bipush        11
>     2558: ldc           #216                // String permutatio
      2560: invokestatic  #184                // Method 
thaumcraft/api/aspects/Aspect.getAspect:(Ljava/lang/String;)Lthaumcraft/api/aspects/Aspect;
      2563: bipush        8
>     2568: ldc           #230                // String perditio
      2570: invokestatic  #184                // Method 
thaumcraft/api/aspects/Aspect.getAspect:(Ljava/lang/String;)Lthaumcraft/api/aspects/Aspect;
      2573: bipush        12
>     2578: ldc_w         #306                // String alienis
      2581: invokestatic  #184                // Method 
thaumcraft/api/aspects/Aspect.getAspect:(Ljava/lang/String;)Lthaumcraft/api/aspects/Aspect;
      2584: bipush        12
>     2589: ldc_w         #280                // String terra
      2592: invokestatic  #184                // Method 
thaumcraft/api/aspects/Aspect.getAspect:(Ljava/lang/String;)Lthaumcraft/api/aspects/Aspect;
      2595: bipush        8
>     2604: ldc_w         #312                // String GADOMANCY.NODE_MANIPULATOR
>     2607: getstatic     #27                 // Field gregtech/api/enums/Mods.Gadomancy:Lgregtech/api/enums/Mods;
      2610: getfield      #31                 // Field gregtech/api/enums/Mods.ID:Ljava/lang/String;
>     2613: ldc           #155                // String BlockNodeManipulator
      2615: lconst_1
      2616: iconst_5
>     2632: ldc_w         #306                // String alienis
      2635: invokestatic  #184                // Method 
thaumcraft/api/aspects/Aspect.getAspect:(Ljava/lang/String;)Lthaumcraft/api/aspects/Aspect;
      2638: bipush        48
>     2643: ldc           #252                // String auram
      2645: invokestatic  #184                // Method 
thaumcraft/api/aspects/Aspect.getAspect:(Ljava/lang/String;)Lthaumcraft/api/aspects/Aspect;
      2648: bipush        64
>     2653: ldc           #232                // String machina
      2655: invokestatic  #184                // Method 
thaumcraft/api/aspects/Aspect.getAspect:(Ljava/lang/String;)Lthaumcraft/api/aspects/Aspect;
      2658: bipush        48
>     2663: ldc           #192                // String praecantatio
      2665: invokestatic  #184                // Method 
thaumcraft/api/aspects/Aspect.getAspect:(Ljava/lang/String;)Lthaumcraft/api/aspects/Aspect;
      2668: bipush        32
>     2673: ldc_w         #314                // String tenebrae
      2676: invokestatic  #184                // Method 
thaumcraft/api/aspects/Aspect.getAspect:(Ljava/lang/String;)Lthaumcraft/api/aspects/Aspect;
      2679: bipush        16
>     2684: ldc           #216                // String permutatio
      2686: invokestatic  #184                // Method 
thaumcraft/api/aspects/Aspect.getAspect:(Ljava/lang/String;)Lthaumcraft/api/aspects/Aspect;
      2689: bipush        24
>     2694: ldc           #190                // String motus
      2696: invokestatic  #184                // Method 
thaumcraft/api/aspects/Aspect.getAspect:(Ljava/lang/String;)Lthaumcraft/api/aspects/Aspect;
      2699: bipush        8
>     2710: ldc_w         #316                // String blockStoneDevice
      2713: lconst_1
      2714: iconst_5
>     2746: ldc           #206                // String ItemResource
      2748: lconst_1
      2749: iconst_0
>     2765: ldc           #206                // String ItemResource
      2767: lconst_1
      2768: bipush        15
>     2785: ldc           #240                // String blockCrystal
      2787: lconst_1
      2788: bipush        6
>     2805: ldc           #60                 // String blockCosmeticSolid
      2807: lconst_1
      2808: bipush        11
>     2825: ldc           #60                 // String blockCosmeticSolid
      2827: lconst_1
      2828: iconst_3
>     2845: ldc_w         #316                // String blockStoneDevice
      2848: lconst_1
      2849: bipush        10
>     2867: ldc           #60                 // String blockCosmeticSolid
      2869: lconst_1
      2870: iconst_3
>     2887: ldc           #60                 // String blockCosmeticSolid
      2889: lconst_1
      2890: bipush        11
>     2908: ldc           #240                // String blockCrystal
      2910: lconst_1
      2911: bipush        6
>     2929: ldc           #206                // String ItemResource
      2931: lconst_1
      2932: bipush        15
>     2950: ldc           #206                // String ItemResource
      2952: lconst_1
      2953: iconst_1
>     2965: ldc_w         #312                // String GADOMANCY.NODE_MANIPULATOR
>     2968: getstatic     #27                 // Field gregtech/api/enums/Mods.Gadomancy:Lgregtech/api/enums/Mods;
      2971: getfield      #31                 // Field gregtech/api/enums/Mods.ID:Ljava/lang/String;
>     2974: ldc           #157                // String BlockStoneMachine
      2976: lconst_1
      2977: iconst_0
>     2993: ldc_w         #306                // String alienis
      2996: invokestatic  #184                // Method 
thaumcraft/api/aspects/Aspect.getAspect:(Ljava/lang/String;)Lthaumcraft/api/aspects/Aspect;
      2999: bipush        24
>     3004: ldc           #232                // String machina
      3006: invokestatic  #184                // Method 
thaumcraft/api/aspects/Aspect.getAspect:(Ljava/lang/String;)Lthaumcraft/api/aspects/Aspect;
      3009: bipush        48
>     3014: ldc           #198                // String ordo
      3016: invokestatic  #184                // Method 
thaumcraft/api/aspects/Aspect.getAspect:(Ljava/lang/String;)Lthaumcraft/api/aspects/Aspect;
      3019: bipush        64
>     3024: ldc           #192                // String praecantatio
      3026: invokestatic  #184                // Method 
thaumcraft/api/aspects/Aspect.getAspect:(Ljava/lang/String;)Lthaumcraft/api/aspects/Aspect;
      3029: bipush        16
>     3034: ldc_w         #314                // String tenebrae
      3037: invokestatic  #184                // Method 
thaumcraft/api/aspects/Aspect.getAspect:(Ljava/lang/String;)Lthaumcraft/api/aspects/Aspect;
      3040: bipush        32
>     3045: ldc_w         #333                // String nebrisum
      3048: invokestatic  #184                // Method 
thaumcraft/api/aspects/Aspect.getAspect:(Ljava/lang/String;)Lthaumcraft/api/aspects/Aspect;
      3051: bipush        8
>     3056: ldc_w         #335                // String lucrum
      3059: invokestatic  #184                // Method 
thaumcraft/api/aspects/Aspect.getAspect:(Ljava/lang/String;)Lthaumcraft/api/aspects/Aspect;
      3062: bipush        16
>     3073: ldc_w         #316                // String blockStoneDevice
      3076: lconst_1
      3077: bipush        8
>     3098: ldc           #206                // String ItemResource
      3100: lconst_1
      3101: bipush        15
>     3118: ldc           #240                // String blockCrystal
      3120: lconst_1
      3121: bipush        6
>     3162: ldc           #240                // String blockCrystal
      3164: lconst_1
      3165: bipush        6
>     3182: ldc           #206                // String ItemResource
      3184: lconst_1
      3185: bipush        15
>     3203: ldc           #240                // String blockCrystal
      3205: lconst_1
      3206: bipush        6
>     3250: ldc           #240                // String blockCrystal
      3252: lconst_1
      3253: bipush        6
>     3266: ldc_w         #312                // String GADOMANCY.NODE_MANIPULATOR
      3269: new           #175                // class thaumcraft/api/aspects/AspectList
      3272: dup
>     3276: ldc_w         #333                // String nebrisum
      3279: invokestatic  #184                // Method 
thaumcraft/api/aspects/Aspect.getAspect:(Ljava/lang/String;)Lthaumcraft/api/aspects/Aspect;
      3282: bipush        27
>     3287: ldc_w         #306                // String alienis
      3290: invokestatic  #184                // Method 
thaumcraft/api/aspects/Aspect.getAspect:(Ljava/lang/String;)Lthaumcraft/api/aspects/Aspect;
      3293: bipush        24
>     3298: ldc_w         #343                // String vacuos
      3301: invokestatic  #184                // Method 
thaumcraft/api/aspects/Aspect.getAspect:(Ljava/lang/String;)Lthaumcraft/api/aspects/Aspect;
      3304: bipush        21
>     3309: ldc           #192                // String praecantatio
      3311: invokestatic  #184                // Method 
thaumcraft/api/aspects/Aspect.getAspect:(Ljava/lang/String;)Lthaumcraft/api/aspects/Aspect;
      3314: bipush        18
>     3319: ldc           #252                // String auram
      3321: invokestatic  #184                // Method 
thaumcraft/api/aspects/Aspect.getAspect:(Ljava/lang/String;)Lthaumcraft/api/aspects/Aspect;
      3324: bipush        15
>     3329: ldc_w         #335                // String lucrum
      3332: invokestatic  #184                // Method 
thaumcraft/api/aspects/Aspect.getAspect:(Ljava/lang/String;)Lthaumcraft/api/aspects/Aspect;
      3335: bipush        12
>     3340: ldc           #232                // String machina
      3342: invokestatic  #184                // Method 
thaumcraft/api/aspects/Aspect.getAspect:(Ljava/lang/String;)Lthaumcraft/api/aspects/Aspect;
      3345: bipush        9
>     3350: ldc_w         #314                // String tenebrae
      3353: invokestatic  #184                // Method 
thaumcraft/api/aspects/Aspect.getAspect:(Ljava/lang/String;)Lthaumcraft/api/aspects/Aspect;
      3356: bipush        6
>     3361: ldc           #216                // String permutatio
      3363: invokestatic  #184                // Method 
thaumcraft/api/aspects/Aspect.getAspect:(Ljava/lang/String;)Lthaumcraft/api/aspects/Aspect;
      3366: iconst_3
>     3370: invokestatic  #220                // Method 
com/dreammaster/thaumcraft/TCHelper.setResearchAspects:(Ljava/lang/String;Lthaumcraft/api/aspects/AspectList;)V
>     3373: ldc_w         #312                // String GADOMANCY.NODE_MANIPULATOR
      3376: iconst_4
>     3377: invokestatic  #224                // Method 
com/dreammaster/thaumcraft/TCHelper.setResearchComplexity:(Ljava/lang/String;I)V
>     3380: ldc_w         #345                // String GADOMANCY.INFUSIONCLAW
>     3383: getstatic     #27                 // Field gregtech/api/enums/Mods.Gadomancy:Lgregtech/api/enums/Mods;
      3386: getfield      #31                 // Field gregtech/api/enums/Mods.ID:Ljava/lang/String;
>     3389: ldc           #159                // String BlockInfusionClaw
      3391: lconst_1
      3392: iconst_0
>     3408: ldc_w         #306                // String alienis
      3411: invokestatic  #184                // Method 
thaumcraft/api/aspects/Aspect.getAspect:(Ljava/lang/String;)Lthaumcraft/api/aspects/Aspect;
      3414: bipush        64
>     3419: ldc           #232                // String machina
      3421: invokestatic  #184                // Method 
thaumcraft/api/aspects/Aspect.getAspect:(Ljava/lang/String;)Lthaumcraft/api/aspects/Aspect;
      3424: bipush        48
>     3429: ldc           #198                // String ordo
      3431: invokestatic  #184                // Method 
thaumcraft/api/aspects/Aspect.getAspect:(Ljava/lang/String;)Lthaumcraft/api/aspects/Aspect;
      3434: bipush        48
>     3439: ldc_w         #314                // String tenebrae
      3442: invokestatic  #184                // Method 
thaumcraft/api/aspects/Aspect.getAspect:(Ljava/lang/String;)Lthaumcraft/api/aspects/Aspect;
      3445: bipush        32
>     3450: ldc           #192                // String praecantatio
      3452: invokestatic  #184                // Method 
thaumcraft/api/aspects/Aspect.getAspect:(Ljava/lang/String;)Lthaumcraft/api/aspects/Aspect;
      3455: bipush        32
>     3460: ldc           #190                // String motus
      3462: invokestatic  #184                // Method 
thaumcraft/api/aspects/Aspect.getAspect:(Ljava/lang/String;)Lthaumcraft/api/aspects/Aspect;
      3465: bipush        16
>     3470: ldc           #196                // String cognitio
      3472: invokestatic  #184                // Method 
thaumcraft/api/aspects/Aspect.getAspect:(Ljava/lang/String;)Lthaumcraft/api/aspects/Aspect;
      3475: bipush        8
>     3486: ldc_w         #316                // String blockStoneDevice
      3489: lconst_1
      3490: iconst_5
>     3510: ldc           #236                // String ItemGolemCore
      3512: lconst_1
      3513: bipush        8
>     3530: ldc           #60                 // String blockCosmeticSolid
      3532: lconst_1
      3533: bipush        6
>     3562: ldc_w         #350                // String FocusPrimal
      3565: lconst_1
      3566: iconst_0
>     3594: ldc           #60                 // String blockCosmeticSolid
      3596: lconst_1
      3597: bipush        6
>     3615: ldc           #202                // String ItemZombieBrain
      3617: lconst_1
      3618: iconst_0
>     3635: ldc           #60                 // String blockCosmeticSolid
      3637: lconst_1
      3638: bipush        6
>     3669: ldc_w         #350                // String FocusPrimal
      3672: lconst_1
      3673: iconst_0
>     3703: ldc           #60                 // String blockCosmeticSolid
      3705: lconst_1
      3706: bipush        6
>     3719: ldc_w         #345                // String GADOMANCY.INFUSIONCLAW
      3722: new           #175                // class thaumcraft/api/aspects/AspectList
      3725: dup
>     3729: ldc_w         #306                // String alienis
      3732: invokestatic  #184                // Method 
thaumcraft/api/aspects/Aspect.getAspect:(Ljava/lang/String;)Lthaumcraft/api/aspects/Aspect;
      3735: bipush        21
>     3740: ldc           #232                // String machina
      3742: invokestatic  #184                // Method 
thaumcraft/api/aspects/Aspect.getAspect:(Ljava/lang/String;)Lthaumcraft/api/aspects/Aspect;
      3745: bipush        18
>     3750: ldc           #192                // String praecantatio
      3752: invokestatic  #184                // Method 
thaumcraft/api/aspects/Aspect.getAspect:(Ljava/lang/String;)Lthaumcraft/api/aspects/Aspect;
      3755: bipush        15
>     3760: ldc           #198                // String ordo
      3762: invokestatic  #184                // Method 
thaumcraft/api/aspects/Aspect.getAspect:(Ljava/lang/String;)Lthaumcraft/api/aspects/Aspect;
      3765: bipush        12
>     3770: ldc_w         #314                // String tenebrae
      3773: invokestatic  #184                // Method 
thaumcraft/api/aspects/Aspect.getAspect:(Ljava/lang/String;)Lthaumcraft/api/aspects/Aspect;
      3776: bipush        9
>     3781: ldc           #190                // String motus
      3783: invokestatic  #184                // Method 
thaumcraft/api/aspects/Aspect.getAspect:(Ljava/lang/String;)Lthaumcraft/api/aspects/Aspect;
      3786: bipush        6
>     3791: ldc           #196                // String cognitio
      3793: invokestatic  #184                // Method 
thaumcraft/api/aspects/Aspect.getAspect:(Ljava/lang/String;)Lthaumcraft/api/aspects/Aspect;
      3796: iconst_3
>     3800: invokestatic  #220                // Method 
com/dreammaster/thaumcraft/TCHelper.setResearchAspects:(Ljava/lang/String;Lthaumcraft/api/aspects/AspectList;)V
>     3803: ldc_w         #345                // String GADOMANCY.INFUSIONCLAW
      3806: iconst_3
>     3807: invokestatic  #224                // Method 
com/dreammaster/thaumcraft/TCHelper.setResearchComplexity:(Ljava/lang/String;I)V
>     3810: ldc_w         #352                // String GADOMANCY.STICKYJAR
      3813: new           #175                // class thaumcraft/api/aspects/AspectList
      3816: dup
>     3820: ldc_w         #354                // String limus
      3823: invokestatic  #184                // Method 
thaumcraft/api/aspects/Aspect.getAspect:(Ljava/lang/String;)Lthaumcraft/api/aspects/Aspect;
      3826: bipush        12
>     3831: ldc_w         #280                // String terra
      3834: invokestatic  #184                // Method 
thaumcraft/api/aspects/Aspect.getAspect:(Ljava/lang/String;)Lthaumcraft/api/aspects/Aspect;
      3837: bipush        9
>     3842: ldc_w         #356                // String aer
      3845: invokestatic  #184                // Method 
thaumcraft/api/aspects/Aspect.getAspect:(Ljava/lang/String;)Lthaumcraft/api/aspects/Aspect;
      3848: bipush        6
>     3853: ldc           #192                // String praecantatio
      3855: invokestatic  #184                // Method 
thaumcraft/api/aspects/Aspect.getAspect:(Ljava/lang/String;)Lthaumcraft/api/aspects/Aspect;
      3858: iconst_3
>     3862: invokestatic  #220                // Method 
com/dreammaster/thaumcraft/TCHelper.setResearchAspects:(Ljava/lang/String;Lthaumcraft/api/aspects/AspectList;)V
>     3865: ldc_w         #352                // String GADOMANCY.STICKYJAR
      3868: iconst_3
>     3869: invokestatic  #224                // Method 
com/dreammaster/thaumcraft/TCHelper.setResearchComplexity:(Ljava/lang/String;I)V
>     3872: ldc_w         #358                // String GADOMANCY.REMOTEJAR
>     3875: getstatic     #27                 // Field gregtech/api/enums/Mods.Gadomancy:Lgregtech/api/enums/Mods;
      3878: getfield      #31                 // Field gregtech/api/enums/Mods.ID:Ljava/lang/String;
>     3881: ldc           #161                // String BlockRemoteJar
      3883: lconst_1
      3884: iconst_0
>     3898: ldc_w         #360                // String aqua
      3901: invokestatic  #184                // Method 
thaumcraft/api/aspects/Aspect.getAspect:(Ljava/lang/String;)Lthaumcraft/api/aspects/Aspect;
      3904: bipush        15
>     3909: ldc_w         #280                // String terra
      3912: invokestatic  #184                // Method 
thaumcraft/api/aspects/Aspect.getAspect:(Ljava/lang/String;)Lthaumcraft/api/aspects/Aspect;
      3915: bipush        15
>     3920: ldc           #198                // String ordo
      3922: invokestatic  #184                // Method 
thaumcraft/api/aspects/Aspect.getAspect:(Ljava/lang/String;)Lthaumcraft/api/aspects/Aspect;
      3925: bipush        15
>     3930: ldc_w         #356                // String aer
      3933: invokestatic  #184                // Method 
thaumcraft/api/aspects/Aspect.getAspect:(Ljava/lang/String;)Lthaumcraft/api/aspects/Aspect;
      3936: bipush        15
>     3948: ldc_w         #284                // String abc
      3951: aastore
      3952: dup
>     3954: ldc_w         #286                // String def
      3957: aastore
      3958: dup
>     3960: ldc_w         #288                // String ghi
      3963: aastore
      3964: dup
>     3980: ldc_w         #362                // String blockCosmeticOpaque
      3983: lconst_1
      3984: iconst_2
>     4009: ldc_w         #364                // String blockJar
      4012: lconst_1
      4013: iconst_0
>     4039: ldc_w         #362                // String blockCosmeticOpaque
      4042: lconst_1
      4043: iconst_2
>     4069: ldc           #204                // String blockMagicalLog
      4071: lconst_1
      4072: iconst_0
>     4098: ldc_w         #366                // String blockMirror
      4101: lconst_1
      4102: bipush        6
>     4129: ldc           #204                // String blockMagicalLog
      4131: lconst_1
      4132: iconst_0
>     4158: ldc           #204                // String blockMagicalLog
      4160: lconst_1
      4161: iconst_0
>     4187: ldc           #204                // String blockMagicalLog
      4189: lconst_1
      4190: iconst_0
>     4216: ldc           #204                // String blockMagicalLog
      4218: lconst_1
      4219: iconst_0
>     4231: ldc_w         #358                // String GADOMANCY.REMOTEJAR
      4234: new           #175                // class thaumcraft/api/aspects/AspectList
      4237: dup
>     4241: ldc           #232                // String machina
      4243: invokestatic  #184                // Method 
thaumcraft/api/aspects/Aspect.getAspect:(Ljava/lang/String;)Lthaumcraft/api/aspects/Aspect;
      4246: bipush        15
>     4251: ldc           #198                // String ordo
      4253: invokestatic  #184                // Method 
thaumcraft/api/aspects/Aspect.getAspect:(Ljava/lang/String;)Lthaumcraft/api/aspects/Aspect;
      4256: bipush        12
>     4261: ldc_w         #360                // String aqua
      4264: invokestatic  #184                // Method 
thaumcraft/api/aspects/Aspect.getAspect:(Ljava/lang/String;)Lthaumcraft/api/aspects/Aspect;
      4267: bipush        9
>     4272: ldc_w         #280                // String terra
      4275: invokestatic  #184                // Method 
thaumcraft/api/aspects/Aspect.getAspect:(Ljava/lang/String;)Lthaumcraft/api/aspects/Aspect;
      4278: bipush        6
>     4283: ldc_w         #306                // String alienis
      4286: invokestatic  #184                // Method 
thaumcraft/api/aspects/Aspect.getAspect:(Ljava/lang/String;)Lthaumcraft/api/aspects/Aspect;
      4289: iconst_3
>     4293: invokestatic  #220                // Method 
com/dreammaster/thaumcraft/TCHelper.setResearchAspects:(Ljava/lang/String;Lthaumcraft/api/aspects/AspectList;)V
>     4296: ldc_w         #358                // String GADOMANCY.REMOTEJAR
      4299: iconst_3
>     4300: invokestatic  #224                // Method 
com/dreammaster/thaumcraft/TCHelper.setResearchComplexity:(Ljava/lang/String;I)V
>     4303: ldc_w         #368                // String GADOMANCY.ARCANEDROPPER
>     4306: getstatic     #27                 // Field gregtech/api/enums/Mods.Gadomancy:Lgregtech/api/enums/Mods;
      4309: getfield      #31                 // Field gregtech/api/enums/Mods.ID:Ljava/lang/String;
>     4312: ldc           #163                // String BlockArcaneDropper
      4314: lconst_1
      4315: iconst_0
>     4329: ldc           #198                // String ordo
      4331: invokestatic  #184                // Method 
thaumcraft/api/aspects/Aspect.getAspect:(Ljava/lang/String;)Lthaumcraft/api/aspects/Aspect;
      4334: bipush        20
>     4339: ldc_w         #356                // String aer
      4342: invokestatic  #184                // Method 
thaumcraft/api/aspects/Aspect.getAspect:(Ljava/lang/String;)Lthaumcraft/api/aspects/Aspect;
      4345: bipush        20
>     4350: ldc_w         #280                // String terra
      4353: invokestatic  #184                // Method 
thaumcraft/api/aspects/Aspect.getAspect:(Ljava/lang/String;)Lthaumcraft/api/aspects/Aspect;
      4356: bipush        20
>     4368: ldc_w         #284                // String abc
      4371: aastore
      4372: dup
>     4374: ldc_w         #286                // String def
      4377: aastore
      4378: dup
>     4380: ldc_w         #288                // String ghi
      4383: aastore
      4384: dup
>     4400: ldc           #60                 // String blockCosmeticSolid
      4402: lconst_1
      4403: bipush        6
>     4429: ldc_w         #373                // String dropper
      4432: lconst_1
      4433: iconst_0
>     4459: ldc           #60                 // String blockCosmeticSolid
      4461: lconst_1
      4462: bipush        6
>     4489: ldc_w         #375                // String blockWoodenDevice
      4492: lconst_1
      4493: iconst_0
>     4519: ldc_w         #377                // String blockMetalDevice
      4522: lconst_1
      4523: bipush        9
>     4550: ldc_w         #375                // String blockWoodenDevice
      4553: lconst_1
      4554: iconst_0
>     4580: ldc           #60                 // String blockCosmeticSolid
      4582: lconst_1
      4583: bipush        6
>     4634: ldc           #60                 // String blockCosmeticSolid
      4636: lconst_1
      4637: bipush        6
>     4650: ldc_w         #368                // String GADOMANCY.ARCANEDROPPER
      4653: new           #175                // class thaumcraft/api/aspects/AspectList
      4656: dup
>     4660: ldc           #232                // String machina
      4662: invokestatic  #184                // Method 
thaumcraft/api/aspects/Aspect.getAspect:(Ljava/lang/String;)Lthaumcraft/api/aspects/Aspect;
      4665: bipush        21
>     4670: ldc_w         #356                // String aer
      4673: invokestatic  #184                // Method 
thaumcraft/api/aspects/Aspect.getAspect:(Ljava/lang/String;)Lthaumcraft/api/aspects/Aspect;
      4676: bipush        18
>     4681: ldc_w         #280                // String terra
      4684: invokestatic  #184                // Method 
thaumcraft/api/aspects/Aspect.getAspect:(Ljava/lang/String;)Lthaumcraft/api/aspects/Aspect;
      4687: bipush        15
>     4692: ldc           #198                // String ordo
      4694: invokestatic  #184                // Method 
thaumcraft/api/aspects/Aspect.getAspect:(Ljava/lang/String;)Lthaumcraft/api/aspects/Aspect;
      4697: bipush        12
>     4702: ldc           #194                // String sensus
      4704: invokestatic  #184                // Method 
thaumcraft/api/aspects/Aspect.getAspect:(Ljava/lang/String;)Lthaumcraft/api/aspects/Aspect;
      4707: bipush        9
>     4712: ldc           #190                // String motus
      4714: invokestatic  #184                // Method 
thaumcraft/api/aspects/Aspect.getAspect:(Ljava/lang/String;)Lthaumcraft/api/aspects/Aspect;
      4717: bipush        6
>     4722: ldc           #192                // String praecantatio
      4724: invokestatic  #184                // Method 
thaumcraft/api/aspects/Aspect.getAspect:(Ljava/lang/String;)Lthaumcraft/api/aspects/Aspect;
      4727: iconst_3
>     4731: invokestatic  #220                // Method 
com/dreammaster/thaumcraft/TCHelper.setResearchAspects:(Ljava/lang/String;Lthaumcraft/api/aspects/AspectList;)V
>     4734: ldc_w         #368                // String GADOMANCY.ARCANEDROPPER
      4737: iconst_3
>     4738: invokestatic  #224                // Method 
com/dreammaster/thaumcraft/TCHelper.setResearchComplexity:(Ljava/lang/String;I)V
>     4741: ldc_w         #382                // String GADOMANCY.ARMORDISGUISE
      4744: new           #175                // class thaumcraft/api/aspects/AspectList
      4747: dup
>     4751: ldc_w         #354                // String limus
      4754: invokestatic  #184                // Method 
thaumcraft/api/aspects/Aspect.getAspect:(Ljava/lang/String;)Lthaumcraft/api/aspects/Aspect;
      4757: bipush        15
>     4762: ldc           #192                // String praecantatio
      4764: invokestatic  #184                // Method 
thaumcraft/api/aspects/Aspect.getAspect:(Ljava/lang/String;)Lthaumcraft/api/aspects/Aspect;
      4767: bipush        12
>     4772: ldc           #250                // String tutamen
      4774: invokestatic  #184                // Method 
thaumcraft/api/aspects/Aspect.getAspect:(Ljava/lang/String;)Lthaumcraft/api/aspects/Aspect;
      4777: bipush        9
>     4782: ldc           #196                // String cognitio
      4784: invokestatic  #184                // Method 
thaumcraft/api/aspects/Aspect.getAspect:(Ljava/lang/String;)Lthaumcraft/api/aspects/Aspect;
      4787: bipush        6
>     4792: ldc_w         #333                // String nebrisum
      4795: invokestatic  #184                // Method 
thaumcraft/api/aspects/Aspect.getAspect:(Ljava/lang/String;)Lthaumcraft/api/aspects/Aspect;
      4798: iconst_3
>     4802: invokestatic  #220                // Method 
com/dreammaster/thaumcraft/TCHelper.setResearchAspects:(Ljava/lang/String;Lthaumcraft/api/aspects/AspectList;)V
>     4805: ldc_w         #382                // String GADOMANCY.ARMORDISGUISE
      4808: iconst_3
>     4809: invokestatic  #224                // Method 
com/dreammaster/thaumcraft/TCHelper.setResearchComplexity:(Ljava/lang/String;I)V
>     4812: ldc_w         #384                // String GADOMANCY.REVEALER
      4815: new           #175                // class thaumcraft/api/aspects/AspectList
      4818: dup
>     4822: ldc_w         #356                // String aer
      4825: invokestatic  #184                // Method 
thaumcraft/api/aspects/Aspect.getAspect:(Ljava/lang/String;)Lthaumcraft/api/aspects/Aspect;
      4828: bipush        15
>     4833: ldc           #194                // String sensus
      4835: invokestatic  #184                // Method 
thaumcraft/api/aspects/Aspect.getAspect:(Ljava/lang/String;)Lthaumcraft/api/aspects/Aspect;
      4838: bipush        12
>     4843: ldc           #192                // String praecantatio
      4845: invokestatic  #184                // Method 
thaumcraft/api/aspects/Aspect.getAspect:(Ljava/lang/String;)Lthaumcraft/api/aspects/Aspect;
      4848: bipush        9
>     4853: ldc_w         #306                // String alienis
      4856: invokestatic  #184                // Method 
thaumcraft/api/aspects/Aspect.getAspect:(Ljava/lang/String;)Lthaumcraft/api/aspects/Aspect;
      4859: bipush        6
>     4864: ldc           #196                // String cognitio
      4866: invokestatic  #184                // Method 
thaumcraft/api/aspects/Aspect.getAspect:(Ljava/lang/String;)Lthaumcraft/api/aspects/Aspect;
      4869: iconst_3
>     4873: invokestatic  #220                // Method 
com/dreammaster/thaumcraft/TCHelper.setResearchAspects:(Ljava/lang/String;Lthaumcraft/api/aspects/AspectList;)V
>     4876: ldc_w         #384                // String GADOMANCY.REVEALER
      4879: iconst_3
>     4880: invokestatic  #224                // Method 
com/dreammaster/thaumcraft/TCHelper.setResearchComplexity:(Ljava/lang/String;I)V
>     4883: ldc_w         #386                // String GADOMANCY.BLOCK_PROTECTOR
      4886: invokestatic  #390                // Method 
com/dreammaster/thaumcraft/TCHelper.clearPages:(Ljava/lang/String;)V
>     4889: ldc_w         #386                // String GADOMANCY.BLOCK_PROTECTOR
      4892: new           #392                // class thaumcraft/api/research/ResearchPage
      4895: dup
>     4896: ldc_w         #394                // String gadomancy.research_page.BLOCK_PROTECTOR.1
      4899: invokespecial #396                // Method 
thaumcraft/api/research/ResearchPage."<init>":(Ljava/lang/String;)V
      4902: invokestatic  #400                // Method 
com/dreammaster/thaumcraft/TCHelper.addResearchPage:(Ljava/lang/String;Lthaumcraft/api/research/ResearchPage;)V
>     4905: ldc_w         #386                // String GADOMANCY.BLOCK_PROTECTOR
>     4908: getstatic     #27                 // Field gregtech/api/enums/Mods.Gadomancy:Lgregtech/api/enums/Mods;
      4911: getfield      #31                 // Field gregtech/api/enums/Mods.ID:Ljava/lang/String;
>     4914: ldc           #157                // String BlockStoneMachine
      4916: lconst_1
      4917: iconst_2
>     4931: ldc_w         #280                // String terra
      4934: invokestatic  #184                // Method 
thaumcraft/api/aspects/Aspect.getAspect:(Ljava/lang/String;)Lthaumcraft/api/aspects/Aspect;
      4937: sipush        150
>     4943: ldc           #198                // String ordo
      4945: invokestatic  #184                // Method 
thaumcraft/api/aspects/Aspect.getAspect:(Ljava/lang/String;)Lthaumcraft/api/aspects/Aspect;
      4948: sipush        150
>     4961: ldc_w         #284                // String abc
      4964: aastore
      4965: dup
>     4967: ldc_w         #286                // String def
      4970: aastore
      4971: dup
>     4973: ldc_w         #288                // String ghi
      4976: aastore
      4977: dup
>     4993: ldc_w         #402                // String potion
      4996: lconst_1
      4997: sipush        8264
>     5024: ldc_w         #404                // String brightNitor
      5027: lconst_1
      5028: iconst_0
>     5054: ldc_w         #402                // String potion
      5057: lconst_1
      5058: sipush        8264
>     5086: ldc_w         #406                // String blockTube
      5089: lconst_1
      5090: iconst_0
>     5116: ldc_w         #364                // String blockJar
      5119: lconst_1
      5120: iconst_0
>     5146: ldc_w         #406                // String blockTube
      5149: lconst_1
      5150: iconst_0
>     5176: ldc           #204                // String blockMagicalLog
      5178: lconst_1
      5179: iconst_0
>     5205: ldc_w         #377                // String blockMetalDevice
      5208: lconst_1
      5209: iconst_0
>     5235: ldc           #204                // String blockMagicalLog
      5237: lconst_1
      5238: iconst_0
>     5250: ldc_w         #386                // String GADOMANCY.BLOCK_PROTECTOR
      5253: new           #392                // class thaumcraft/api/research/ResearchPage
      5256: dup
>     5257: getstatic     #27                 // Field gregtech/api/enums/Mods.Gadomancy:Lgregtech/api/enums/Mods;
      5260: getfield      #31                 // Field gregtech/api/enums/Mods.ID:Ljava/lang/String;
>     5263: ldc           #157                // String BlockStoneMachine
      5265: lconst_1
      5266: iconst_2
>     5282: ldc_w         #386                // String GADOMANCY.BLOCK_PROTECTOR
      5285: new           #392                // class thaumcraft/api/research/ResearchPage
      5288: dup
>     5289: ldc_w         #415                // String gadomancy.research_page.BLOCK_PROTECTOR.3
      5292: invokespecial #396                // Method 
thaumcraft/api/research/ResearchPage."<init>":(Ljava/lang/String;)V
      5295: invokestatic  #400                // Method 
com/dreammaster/thaumcraft/TCHelper.addResearchPage:(Ljava/lang/String;Lthaumcraft/api/research/ResearchPage;)V
>     5298: ldc_w         #386                // String GADOMANCY.BLOCK_PROTECTOR
      5301: new           #392                // class thaumcraft/api/research/ResearchPage
      5304: dup
>     5305: ldc_w         #417                // String gadomancy.research_page.BLOCK_PROTECTOR.4
      5308: invokespecial #396                // Method 
thaumcraft/api/research/ResearchPage."<init>":(Ljava/lang/String;)V
      5311: invokestatic  #400                // Method 
com/dreammaster/thaumcraft/TCHelper.addResearchPage:(Ljava/lang/String;Lthaumcraft/api/research/ResearchPage;)V
>     5314: ldc_w         #386                // String GADOMANCY.BLOCK_PROTECTOR
      5317: new           #175                // class thaumcraft/api/aspects/AspectList
      5320: dup
>     5324: ldc           #196                // String cognitio
      5326: invokestatic  #184                // Method 
thaumcraft/api/aspects/Aspect.getAspect:(Ljava/lang/String;)Lthaumcraft/api/aspects/Aspect;
      5329: bipush        21
>     5334: ldc_w         #419                // String bestia
      5337: invokestatic  #184                // Method 
thaumcraft/api/aspects/Aspect.getAspect:(Ljava/lang/String;)Lthaumcraft/api/aspects/Aspect;
      5340: bipush        18
>     5345: ldc_w         #280                // String terra
      5348: invokestatic  #184                // Method 
thaumcraft/api/aspects/Aspect.getAspect:(Ljava/lang/String;)Lthaumcraft/api/aspects/Aspect;
      5351: bipush        15
>     5356: ldc           #198                // String ordo
      5358: invokestatic  #184                // Method 
thaumcraft/api/aspects/Aspect.getAspect:(Ljava/lang/String;)Lthaumcraft/api/aspects/Aspect;
      5361: bipush        12
>     5366: ldc           #252                // String auram
      5368: invokestatic  #184                // Method 
thaumcraft/api/aspects/Aspect.getAspect:(Ljava/lang/String;)Lthaumcraft/api/aspects/Aspect;
      5371: bipush        9
>     5376: ldc_w         #421                // String lux
      5379: invokestatic  #184                // Method 
thaumcraft/api/aspects/Aspect.getAspect:(Ljava/lang/String;)Lthaumcraft/api/aspects/Aspect;
      5382: bipush        6
>     5387: ldc           #250                // String tutamen
      5389: invokestatic  #184                // Method 
thaumcraft/api/aspects/Aspect.getAspect:(Ljava/lang/String;)Lthaumcraft/api/aspects/Aspect;
      5392: iconst_3
>     5396: invokestatic  #220                // Method 
com/dreammaster/thaumcraft/TCHelper.setResearchAspects:(Ljava/lang/String;Lthaumcraft/api/aspects/AspectList;)V
>     5399: ldc_w         #386                // String GADOMANCY.BLOCK_PROTECTOR
      5402: iconst_3
>     5403: invokestatic  #224                // Method 
com/dreammaster/thaumcraft/TCHelper.setResearchComplexity:(Ljava/lang/String;I)V
>     5406: ldc_w         #423                // String GADOMANCY.E_PORTAL_CREATOR
>     5409: getstatic     #27                 // Field gregtech/api/enums/Mods.Gadomancy:Lgregtech/api/enums/Mods;
      5412: getfield      #31                 // Field gregtech/api/enums/Mods.ID:Ljava/lang/String;
>     5415: ldc           #157                // String BlockStoneMachine
      5417: lconst_1
      5418: iconst_1
>     5432: ldc           #230                // String perditio
      5434: invokestatic  #184                // Method 
thaumcraft/api/aspects/Aspect.getAspect:(Ljava/lang/String;)Lthaumcraft/api/aspects/Aspect;
      5437: bipush        30
>     5442: ldc           #198                // String ordo
      5444: invokestatic  #184                // Method 
thaumcraft/api/aspects/Aspect.getAspect:(Ljava/lang/String;)Lthaumcraft/api/aspects/Aspect;
      5447: bipush        30
>     5452: ldc_w         #280                // String terra
      5455: invokestatic  #184                // Method 
thaumcraft/api/aspects/Aspect.getAspect:(Ljava/lang/String;)Lthaumcraft/api/aspects/Aspect;
      5458: bipush        30
>     5470: ldc_w         #284                // String abc
      5473: aastore
      5474: dup
>     5476: ldc_w         #286                // String def
      5479: aastore
      5480: dup
>     5482: ldc_w         #288                // String ghi
      5485: aastore
      5486: dup
>     5502: ldc           #60                 // String blockCosmeticSolid
      5504: lconst_1
      5505: bipush        11
>     5531: ldc           #60                 // String blockCosmeticSolid
      5533: lconst_1
      5534: bipush        15
>     5561: ldc           #60                 // String blockCosmeticSolid
      5563: lconst_1
      5564: bipush        11
>     5591: ldc           #240                // String blockCrystal
      5593: lconst_1
      5594: bipush        6
>     5621: ldc           #60                 // String blockCosmeticSolid
      5623: lconst_1
      5624: bipush        11
>     5651: ldc           #240                // String blockCrystal
      5653: lconst_1
      5654: bipush        6
>     5681: ldc           #60                 // String blockCosmeticSolid
      5683: lconst_1
      5684: bipush        11
>     5711: ldc           #60                 // String blockCosmeticSolid
      5713: lconst_1
      5714: bipush        15
>     5741: ldc           #60                 // String blockCosmeticSolid
      5743: lconst_1
      5744: bipush        11
>     5757: ldc_w         #423                // String GADOMANCY.E_PORTAL_CREATOR
>     5760: getstatic     #27                 // Field gregtech/api/enums/Mods.Gadomancy:Lgregtech/api/enums/Mods;
      5763: getfield      #31                 // Field gregtech/api/enums/Mods.ID:Ljava/lang/String;
>     5766: ldc           #157                // String BlockStoneMachine
      5768: lconst_1
      5769: iconst_3
>     5785: ldc_w         #306                // String alienis
      5788: invokestatic  #184                // Method 
thaumcraft/api/aspects/Aspect.getAspect:(Ljava/lang/String;)Lthaumcraft/api/aspects/Aspect;
      5791: bipush        48
>     5796: ldc           #232                // String machina
      5798: invokestatic  #184                // Method 
thaumcraft/api/aspects/Aspect.getAspect:(Ljava/lang/String;)Lthaumcraft/api/aspects/Aspect;
      5801: bipush        48
>     5806: ldc           #216                // String permutatio
      5808: invokestatic  #184                // Method 
thaumcraft/api/aspects/Aspect.getAspect:(Ljava/lang/String;)Lthaumcraft/api/aspects/Aspect;
      5811: bipush        64
>     5816: ldc_w         #314                // String tenebrae
      5819: invokestatic  #184                // Method 
thaumcraft/api/aspects/Aspect.getAspect:(Ljava/lang/String;)Lthaumcraft/api/aspects/Aspect;
      5822: bipush        32
>     5827: ldc_w         #343                // String vacuos
      5830: invokestatic  #184                // Method 
thaumcraft/api/aspects/Aspect.getAspect:(Ljava/lang/String;)Lthaumcraft/api/aspects/Aspect;
      5833: bipush        32
>     5838: ldc           #252                // String auram
      5840: invokestatic  #184                // Method 
thaumcraft/api/aspects/Aspect.getAspect:(Ljava/lang/String;)Lthaumcraft/api/aspects/Aspect;
      5843: bipush        16
>     5848: ldc           #192                // String praecantatio
      5850: invokestatic  #184                // Method 
thaumcraft/api/aspects/Aspect.getAspect:(Ljava/lang/String;)Lthaumcraft/api/aspects/Aspect;
      5853: bipush        8
>     5864: ldc_w         #316                // String blockStoneDevice
      5867: lconst_1
      5868: bipush        8
>     5889: ldc_w         #298                // String ItemEldritchObject
      5892: lconst_1
      5893: iconst_0
>     5909: ldc           #240                // String blockCrystal
      5911: lconst_1
      5912: iconst_5
>     5952: ldc           #240                // String blockCrystal
      5954: lconst_1
      5955: iconst_5
>     5971: ldc_w         #298                // String ItemEldritchObject
      5974: lconst_1
      5975: iconst_0
>     5992: ldc           #240                // String blockCrystal
      5994: lconst_1
      5995: iconst_5
>     6038: ldc           #240                // String blockCrystal
      6040: lconst_1
      6041: iconst_5
>     6053: ldc_w         #423                // String GADOMANCY.E_PORTAL_CREATOR
      6056: new           #175                // class thaumcraft/api/aspects/AspectList
      6059: dup
>     6063: ldc_w         #314                // String tenebrae
      6066: invokestatic  #184                // Method 
thaumcraft/api/aspects/Aspect.getAspect:(Ljava/lang/String;)Lthaumcraft/api/aspects/Aspect;
      6069: bipush        21
>     6074: ldc           #252                // String auram
      6076: invokestatic  #184                // Method 
thaumcraft/api/aspects/Aspect.getAspect:(Ljava/lang/String;)Lthaumcraft/api/aspects/Aspect;
      6079: bipush        18
>     6084: ldc_w         #425                // String iter
      6087: invokestatic  #184                // Method 
thaumcraft/api/aspects/Aspect.getAspect:(Ljava/lang/String;)Lthaumcraft/api/aspects/Aspect;
      6090: bipush        15
>     6095: ldc_w         #306                // String alienis
      6098: invokestatic  #184                // Method 
thaumcraft/api/aspects/Aspect.getAspect:(Ljava/lang/String;)Lthaumcraft/api/aspects/Aspect;
      6101: bipush        12
>     6106: ldc_w         #343                // String vacuos
      6109: invokestatic  #184                // Method 
thaumcraft/api/aspects/Aspect.getAspect:(Ljava/lang/String;)Lthaumcraft/api/aspects/Aspect;
      6112: bipush        9
>     6117: ldc           #232                // String machina
      6119: invokestatic  #184                // Method 
thaumcraft/api/aspects/Aspect.getAspect:(Ljava/lang/String;)Lthaumcraft/api/aspects/Aspect;
      6122: bipush        6
>     6127: ldc           #192                // String praecantatio
      6129: invokestatic  #184                // Method 
thaumcraft/api/aspects/Aspect.getAspect:(Ljava/lang/String;)Lthaumcraft/api/aspects/Aspect;
      6132: iconst_3
>     6136: invokestatic  #220                // Method 
com/dreammaster/thaumcraft/TCHelper.setResearchAspects:(Ljava/lang/String;Lthaumcraft/api/aspects/AspectList;)V
>     6139: ldc_w         #423                // String GADOMANCY.E_PORTAL_CREATOR
      6142: iconst_3
>     6143: invokestatic  #224                // Method 
com/dreammaster/thaumcraft/TCHelper.setResearchComplexity:(Ljava/lang/String;I)V
>     6146: ldc_w         #427                // String GADOMANCY.ETHEREAL_FAMILIAR
      6149: new           #175                // class thaumcraft/api/aspects/AspectList
      6152: dup
>     6156: ldc_w         #280                // String terra
      6159: invokestatic  #184                // Method 
thaumcraft/api/aspects/Aspect.getAspect:(Ljava/lang/String;)Lthaumcraft/api/aspects/Aspect;
      6162: bipush        18
>     6167: ldc           #192                // String praecantatio
      6169: invokestatic  #184                // Method 
thaumcraft/api/aspects/Aspect.getAspect:(Ljava/lang/String;)Lthaumcraft/api/aspects/Aspect;
      6172: bipush        15
>     6177: ldc_w         #282                // String ignis
      6180: invokestatic  #184                // Method 
thaumcraft/api/aspects/Aspect.getAspect:(Ljava/lang/String;)Lthaumcraft/api/aspects/Aspect;
      6183: bipush        12
>     6188: ldc           #252                // String auram
      6190: invokestatic  #184                // Method 
thaumcraft/api/aspects/Aspect.getAspect:(Ljava/lang/String;)Lthaumcraft/api/aspects/Aspect;
      6193: bipush        9
>     6198: ldc_w         #356                // String aer
      6201: invokestatic  #184                // Method 
thaumcraft/api/aspects/Aspect.getAspect:(Ljava/lang/String;)Lthaumcraft/api/aspects/Aspect;
      6204: bipush        6
>     6209: ldc           #198                // String ordo
      6211: invokestatic  #184                // Method 
thaumcraft/api/aspects/Aspect.getAspect:(Ljava/lang/String;)Lthaumcraft/api/aspects/Aspect;
      6214: iconst_3
>     6218: invokestatic  #220                // Method 
com/dreammaster/thaumcraft/TCHelper.setResearchAspects:(Ljava/lang/String;Lthaumcraft/api/aspects/AspectList;)V
>     6221: ldc_w         #427                // String GADOMANCY.ETHEREAL_FAMILIAR
      6224: iconst_3
>     6225: invokestatic  #224                // Method 
com/dreammaster/thaumcraft/TCHelper.setResearchComplexity:(Ljava/lang/String;I)V
>     6228: ldc_w         #429                // String GADOMANCY.AURA_CORE
      6231: new           #175                // class thaumcraft/api/aspects/AspectList
      6234: dup
>     6238: ldc_w         #314                // String tenebrae
      6241: invokestatic  #184                // Method 
thaumcraft/api/aspects/Aspect.getAspect:(Ljava/lang/String;)Lthaumcraft/api/aspects/Aspect;
      6244: bipush        27
>     6249: ldc           #192                // String praecantatio
      6251: invokestatic  #184                // Method 
thaumcraft/api/aspects/Aspect.getAspect:(Ljava/lang/String;)Lthaumcraft/api/aspects/Aspect;
      6254: bipush        24
>     6259: ldc           #252                // String auram
      6261: invokestatic  #184                // Method 
thaumcraft/api/aspects/Aspect.getAspect:(Ljava/lang/String;)Lthaumcraft/api/aspects/Aspect;
      6264: bipush        21
>     6269: ldc           #230                // String perditio
      6271: invokestatic  #184                // Method 
thaumcraft/api/aspects/Aspect.getAspect:(Ljava/lang/String;)Lthaumcraft/api/aspects/Aspect;
      6274: bipush        18
>     6279: ldc           #198                // String ordo
      6281: invokestatic  #184                // Method 
thaumcraft/api/aspects/Aspect.getAspect:(Ljava/lang/String;)Lthaumcraft/api/aspects/Aspect;
      6284: bipush        15
>     6289: ldc_w         #360                // String aqua
      6292: invokestatic  #184                // Method 
thaumcraft/api/aspects/Aspect.getAspect:(Ljava/lang/String;)Lthaumcraft/api/aspects/Aspect;
      6295: bipush        12
>     6300: ldc_w         #356                // String aer
      6303: invokestatic  #184                // Method 
thaumcraft/api/aspects/Aspect.getAspect:(Ljava/lang/String;)Lthaumcraft/api/aspects/Aspect;
      6306: bipush        9
>     6311: ldc_w         #282                // String ignis
      6314: invokestatic  #184                // Method 
thaumcraft/api/aspects/Aspect.getAspect:(Ljava/lang/String;)Lthaumcraft/api/aspects/Aspect;
      6317: bipush        6
>     6322: ldc_w         #280                // String terra
      6325: invokestatic  #184                // Method 
thaumcraft/api/aspects/Aspect.getAspect:(Ljava/lang/String;)Lthaumcraft/api/aspects/Aspect;
      6328: iconst_3
>     6332: invokestatic  #220                // Method 
com/dreammaster/thaumcraft/TCHelper.setResearchAspects:(Ljava/lang/String;Lthaumcraft/api/aspects/AspectList;)V
>     6335: ldc_w         #429                // String GADOMANCY.AURA_CORE
      6338: iconst_3
>     6339: invokestatic  #224                // Method 
com/dreammaster/thaumcraft/TCHelper.setResearchComplexity:(Ljava/lang/String;I)V
>     6342: ldc_w         #431                // String GADOMANCY.CLEAN_AURA_CORE
      6345: new           #175                // class thaumcraft/api/aspects/AspectList
      6348: dup
>     6352: ldc_w         #360                // String aqua
      6355: invokestatic  #184                // Method 
thaumcraft/api/aspects/Aspect.getAspect:(Ljava/lang/String;)Lthaumcraft/api/aspects/Aspect;
      6358: bipush        27
>     6363: ldc_w         #433                // String sano
      6366: invokestatic  #184                // Method 
thaumcraft/api/aspects/Aspect.getAspect:(Ljava/lang/String;)Lthaumcraft/api/aspects/Aspect;
      6369: bipush        24
>     6374: ldc           #192                // String praecantatio
      6376: invokestatic  #184                // Method 
thaumcraft/api/aspects/Aspect.getAspect:(Ljava/lang/String;)Lthaumcraft/api/aspects/Aspect;
      6379: bipush        21
>     6384: ldc           #252                // String auram
      6386: invokestatic  #184                // Method 
thaumcraft/api/aspects/Aspect.getAspect:(Ljava/lang/String;)Lthaumcraft/api/aspects/Aspect;
      6389: bipush        18
>     6394: ldc_w         #280                // String terra
      6397: invokestatic  #184                // Method 
thaumcraft/api/aspects/Aspect.getAspect:(Ljava/lang/String;)Lthaumcraft/api/aspects/Aspect;
      6400: bipush        15
>     6405: ldc_w         #282                // String ignis
      6408: invokestatic  #184                // Method 
thaumcraft/api/aspects/Aspect.getAspect:(Ljava/lang/String;)Lthaumcraft/api/aspects/Aspect;
      6411: bipush        12
>     6416: ldc           #230                // String perditio
      6418: invokestatic  #184                // Method 
thaumcraft/api/aspects/Aspect.getAspect:(Ljava/lang/String;)Lthaumcraft/api/aspects/Aspect;
      6421: bipush        9
>     6426: ldc           #198                // String ordo
      6428: invokestatic  #184                // Method 
thaumcraft/api/aspects/Aspect.getAspect:(Ljava/lang/String;)Lthaumcraft/api/aspects/Aspect;
      6431: bipush        6
>     6436: ldc_w         #356                // String aer
      6439: invokestatic  #184                // Method 
thaumcraft/api/aspects/Aspect.getAspect:(Ljava/lang/String;)Lthaumcraft/api/aspects/Aspect;
      6442: iconst_3
>     6446: invokestatic  #220                // Method 
com/dreammaster/thaumcraft/TCHelper.setResearchAspects:(Ljava/lang/String;Lthaumcraft/api/aspects/AspectList;)V
>     6449: ldc_w         #431                // String GADOMANCY.CLEAN_AURA_CORE
      6452: iconst_4
>     6453: invokestatic  #224                // Method 
com/dreammaster/thaumcraft/TCHelper.setResearchComplexity:(Ljava/lang/String;I)V
>     6456: ldc_w         #435                // String GADOMANCY.FAMILIAR_POISON
      6459: new           #175                // class thaumcraft/api/aspects/AspectList
      6462: dup
>     6466: ldc_w         #437                // String venenum
      6469: invokestatic  #184                // Method 
thaumcraft/api/aspects/Aspect.getAspect:(Ljava/lang/String;)Lthaumcraft/api/aspects/Aspect;
      6472: bipush        15
>     6477: ldc           #248                // String telum
      6479: invokestatic  #184                // Method 
thaumcraft/api/aspects/Aspect.getAspect:(Ljava/lang/String;)Lthaumcraft/api/aspects/Aspect;
      6482: bipush        12
>     6487: ldc           #230                // String perditio
      6489: invokestatic  #184                // Method 
thaumcraft/api/aspects/Aspect.getAspect:(Ljava/lang/String;)Lthaumcraft/api/aspects/Aspect;
      6492: bipush        9
>     6497: ldc_w         #314                // String tenebrae
      6500: invokestatic  #184                // Method 
thaumcraft/api/aspects/Aspect.getAspect:(Ljava/lang/String;)Lthaumcraft/api/aspects/Aspect;
      6503: bipush        6
>     6508: ldc           #192                // String praecantatio
      6510: invokestatic  #184                // Method 
thaumcraft/api/aspects/Aspect.getAspect:(Ljava/lang/String;)Lthaumcraft/api/aspects/Aspect;
      6513: iconst_3
>     6517: invokestatic  #220                // Method 
com/dreammaster/thaumcraft/TCHelper.setResearchAspects:(Ljava/lang/String;Lthaumcraft/api/aspects/AspectList;)V
>     6520: ldc_w         #435                // String GADOMANCY.FAMILIAR_POISON
      6523: iconst_3
>     6524: invokestatic  #224                // Method 
com/dreammaster/thaumcraft/TCHelper.setResearchComplexity:(Ljava/lang/String;I)V
>     6527: ldc_w         #439                // String GADOMANCY.FAMILIAR_WEAKNESS
      6530: new           #175                // class thaumcraft/api/aspects/AspectList
      6533: dup
>     6537: ldc_w         #441                // String vinculum
      6540: invokestatic  #184                // Method 
thaumcraft/api/aspects/Aspect.getAspect:(Ljava/lang/String;)Lthaumcraft/api/aspects/Aspect;
      6543: bipush        15
>     6548: ldc_w         #443                // String vitium
      6551: invokestatic  #184                // Method 
thaumcraft/api/aspects/Aspect.getAspect:(Ljava/lang/String;)Lthaumcraft/api/aspects/Aspect;
      6554: bipush        12
>     6559: ldc           #248                // String telum
      6561: invokestatic  #184                // Method 
thaumcraft/api/aspects/Aspect.getAspect:(Ljava/lang/String;)Lthaumcraft/api/aspects/Aspect;
      6564: bipush        9
>     6569: ldc           #192                // String praecantatio
      6571: invokestatic  #184                // Method 
thaumcraft/api/aspects/Aspect.getAspect:(Ljava/lang/String;)Lthaumcraft/api/aspects/Aspect;
      6574: bipush        6
>     6579: ldc_w         #314                // String tenebrae
      6582: invokestatic  #184                // Method 
thaumcraft/api/aspects/Aspect.getAspect:(Ljava/lang/String;)Lthaumcraft/api/aspects/Aspect;
      6585: iconst_3
>     6589: invokestatic  #220                // Method 
com/dreammaster/thaumcraft/TCHelper.setResearchAspects:(Ljava/lang/String;Lthaumcraft/api/aspects/AspectList;)V
>     6592: ldc_w         #439                // String GADOMANCY.FAMILIAR_WEAKNESS
      6595: iconst_3
>     6596: invokestatic  #224                // Method 
com/dreammaster/thaumcraft/TCHelper.setResearchComplexity:(Ljava/lang/String;I)V
>     6599: ldc_w         #445                // String GADOMANCY.FAMILIAR_SHOCK
      6602: new           #175                // class thaumcraft/api/aspects/AspectList
      6605: dup
>     6609: ldc_w         #356                // String aer
      6612: invokestatic  #184                // Method 
thaumcraft/api/aspects/Aspect.getAspect:(Ljava/lang/String;)Lthaumcraft/api/aspects/Aspect;
      6615: bipush        15
>     6620: ldc_w         #447                // String tempestas
      6623: invokestatic  #184                // Method 
thaumcraft/api/aspects/Aspect.getAspect:(Ljava/lang/String;)Lthaumcraft/api/aspects/Aspect;
      6626: bipush        12
>     6631: ldc           #248                // String telum
      6633: invokestatic  #184                // Method 
thaumcraft/api/aspects/Aspect.getAspect:(Ljava/lang/String;)Lthaumcraft/api/aspects/Aspect;
      6636: bipush        9
>     6641: ldc           #192                // String praecantatio
      6643: invokestatic  #184                // Method 
thaumcraft/api/aspects/Aspect.getAspect:(Ljava/lang/String;)Lthaumcraft/api/aspects/Aspect;
      6646: bipush        6
>     6651: ldc_w         #314                // String tenebrae
      6654: invokestatic  #184                // Method 
thaumcraft/api/aspects/Aspect.getAspect:(Ljava/lang/String;)Lthaumcraft/api/aspects/Aspect;
      6657: iconst_3
>     6661: invokestatic  #220                // Method 
com/dreammaster/thaumcraft/TCHelper.setResearchAspects:(Ljava/lang/String;Lthaumcraft/api/aspects/AspectList;)V
>     6664: ldc_w         #445                // String GADOMANCY.FAMILIAR_SHOCK
      6667: iconst_3
>     6668: invokestatic  #224                // Method 
com/dreammaster/thaumcraft/TCHelper.setResearchComplexity:(Ljava/lang/String;I)V
>     6671: ldc_w         #449                // String GADOMANCY.FAMILIAR_FIRE
      6674: new           #175                // class thaumcraft/api/aspects/AspectList
      6677: dup
>     6681: ldc_w         #282                // String ignis
      6684: invokestatic  #184                // Method 
thaumcraft/api/aspects/Aspect.getAspect:(Ljava/lang/String;)Lthaumcraft/api/aspects/Aspect;
      6687: bipush        15
>     6692: ldc_w         #451                // String infernus
      6695: invokestatic  #184                // Method 
thaumcraft/api/aspects/Aspect.getAspect:(Ljava/lang/String;)Lthaumcraft/api/aspects/Aspect;
      6698: bipush        12
>     6703: ldc           #248                // String telum
      6705: invokestatic  #184                // Method 
thaumcraft/api/aspects/Aspect.getAspect:(Ljava/lang/String;)Lthaumcraft/api/aspects/Aspect;
      6708: bipush        9
>     6713: ldc           #192                // String praecantatio
      6715: invokestatic  #184                // Method 
thaumcraft/api/aspects/Aspect.getAspect:(Ljava/lang/String;)Lthaumcraft/api/aspects/Aspect;
      6718: bipush        6
>     6723: ldc_w         #314                // String tenebrae
      6726: invokestatic  #184                // Method 
thaumcraft/api/aspects/Aspect.getAspect:(Ljava/lang/String;)Lthaumcraft/api/aspects/Aspect;
      6729: iconst_3
>     6733: invokestatic  #220                // Method 
com/dreammaster/thaumcraft/TCHelper.setResearchAspects:(Ljava/lang/String;Lthaumcraft/api/aspects/AspectList;)V
>     6736: ldc_w         #449                // String GADOMANCY.FAMILIAR_FIRE
      6739: iconst_3
>     6740: invokestatic  #224                // Method 
com/dreammaster/thaumcraft/TCHelper.setResearchComplexity:(Ljava/lang/String;I)V
>     6743: ldc_w         #453                // String GADOMANCY.FAMILIAR_DAMAGE
      6746: new           #175                // class thaumcraft/api/aspects/AspectList
      6749: dup
>     6753: ldc_w         #455                // String potentia
      6756: invokestatic  #184                // Method 
thaumcraft/api/aspects/Aspect.getAspect:(Ljava/lang/String;)Lthaumcraft/api/aspects/Aspect;
      6759: bipush        15
>     6764: ldc_w         #282                // String ignis
      6767: invokestatic  #184                // Method 
thaumcraft/api/aspects/Aspect.getAspect:(Ljava/lang/String;)Lthaumcraft/api/aspects/Aspect;
      6770: bipush        12
>     6775: ldc           #248                // String telum
      6777: invokestatic  #184                // Method 
thaumcraft/api/aspects/Aspect.getAspect:(Ljava/lang/String;)Lthaumcraft/api/aspects/Aspect;
      6780: bipush        9
>     6785: ldc           #192                // String praecantatio
      6787: invokestatic  #184                // Method 
thaumcraft/api/aspects/Aspect.getAspect:(Ljava/lang/String;)Lthaumcraft/api/aspects/Aspect;
      6790: bipush        6
>     6795: ldc_w         #314                // String tenebrae
      6798: invokestatic  #184                // Method 
thaumcraft/api/aspects/Aspect.getAspect:(Ljava/lang/String;)Lthaumcraft/api/aspects/Aspect;
      6801: iconst_3
>     6805: invokestatic  #220                // Method 
com/dreammaster/thaumcraft/TCHelper.setResearchAspects:(Ljava/lang/String;Lthaumcraft/api/aspects/AspectList;)V
>     6808: ldc_w         #453                // String GADOMANCY.FAMILIAR_DAMAGE
      6811: iconst_3
>     6812: invokestatic  #224                // Method 
com/dreammaster/thaumcraft/TCHelper.setResearchComplexity:(Ljava/lang/String;I)V
>     6815: ldc_w         #457                // String GADOMANCY.FAMILIAR_RANGE
      6818: new           #175                // class thaumcraft/api/aspects/AspectList
      6821: dup
>     6825: ldc_w         #306                // String alienis
      6828: invokestatic  #184                // Method 
thaumcraft/api/aspects/Aspect.getAspect:(Ljava/lang/String;)Lthaumcraft/api/aspects/Aspect;
      6831: bipush        15
>     6836: ldc           #198                // String ordo
      6838: invokestatic  #184                // Method 
thaumcraft/api/aspects/Aspect.getAspect:(Ljava/lang/String;)Lthaumcraft/api/aspects/Aspect;
      6841: bipush        12
>     6846: ldc           #248                // String telum
      6848: invokestatic  #184                // Method 
thaumcraft/api/aspects/Aspect.getAspect:(Ljava/lang/String;)Lthaumcraft/api/aspects/Aspect;
      6851: bipush        9
>     6856: ldc           #192                // String praecantatio
      6858: invokestatic  #184                // Method 
thaumcraft/api/aspects/Aspect.getAspect:(Ljava/lang/String;)Lthaumcraft/api/aspects/Aspect;
      6861: bipush        6
>     6866: ldc_w         #314                // String tenebrae
      6869: invokestatic  #184                // Method 
thaumcraft/api/aspects/Aspect.getAspect:(Ljava/lang/String;)Lthaumcraft/api/aspects/Aspect;
      6872: iconst_3
>     6876: invokestatic  #220                // Method 
com/dreammaster/thaumcraft/TCHelper.setResearchAspects:(Ljava/lang/String;Lthaumcraft/api/aspects/AspectList;)V
>     6879: ldc_w         #457                // String GADOMANCY.FAMILIAR_RANGE
      6882: iconst_3
>     6883: invokestatic  #224                // Method 
com/dreammaster/thaumcraft/TCHelper.setResearchComplexity:(Ljava/lang/String;I)V
>     6886: ldc_w         #459                // String GADOMANCY.FAMILIAR_SPEED
      6889: new           #175                // class thaumcraft/api/aspects/AspectList
      6892: dup
>     6896: ldc           #190                // String motus
      6898: invokestatic  #184                // Method 
thaumcraft/api/aspects/Aspect.getAspect:(Ljava/lang/String;)Lthaumcraft/api/aspects/Aspect;
      6901: bipush        15
>     6906: ldc           #252                // String auram
      6908: invokestatic  #184                // Method 
thaumcraft/api/aspects/Aspect.getAspect:(Ljava/lang/String;)Lthaumcraft/api/aspects/Aspect;
      6911: bipush        12
>     6916: ldc           #248                // String telum
      6918: invokestatic  #184                // Method 
thaumcraft/api/aspects/Aspect.getAspect:(Ljava/lang/String;)Lthaumcraft/api/aspects/Aspect;
      6921: bipush        9
>     6926: ldc           #192                // String praecantatio
      6928: invokestatic  #184                // Method 
thaumcraft/api/aspects/Aspect.getAspect:(Ljava/lang/String;)Lthaumcraft/api/aspects/Aspect;
      6931: bipush        6
>     6936: ldc_w         #314                // String tenebrae
      6939: invokestatic  #184                // Method 
thaumcraft/api/aspects/Aspect.getAspect:(Ljava/lang/String;)Lthaumcraft/api/aspects/Aspect;
      6942: iconst_3
>     6946: invokestatic  #220                // Method 
com/dreammaster/thaumcraft/TCHelper.setResearchAspects:(Ljava/lang/String;Lthaumcraft/api/aspects/AspectList;)V
>     6949: ldc_w         #459                // String GADOMANCY.FAMILIAR_SPEED
      6952: iconst_3
>     6953: invokestatic  #224                // Method 
com/dreammaster/thaumcraft/TCHelper.setResearchComplexity:(Ljava/lang/String;I)V
>     6956: ldc_w         #461                // String GADOMANCY.ARCANE_PACKAGER
>     6959: getstatic     #27                 // Field gregtech/api/enums/Mods.Gadomancy:Lgregtech/api/enums/Mods;
      6962: getfield      #31                 // Field gregtech/api/enums/Mods.ID:Ljava/lang/String;
>     6965: ldc           #157                // String BlockStoneMachine
      6967: lconst_1
      6968: iconst_4
>     6982: ldc           #198                // String ordo
      6984: invokestatic  #184                // Method 
thaumcraft/api/aspects/Aspect.getAspect:(Ljava/lang/String;)Lthaumcraft/api/aspects/Aspect;
      6987: bipush        100
>     6992: ldc           #230                // String perditio
      6994: invokestatic  #184                // Method 
thaumcraft/api/aspects/Aspect.getAspect:(Ljava/lang/String;)Lthaumcraft/api/aspects/Aspect;
      6997: bipush        100
>     7002: ldc_w         #356                // String aer
      7005: invokestatic  #184                // Method 
thaumcraft/api/aspects/Aspect.getAspect:(Ljava/lang/String;)Lthaumcraft/api/aspects/Aspect;
      7008: bipush        100
>     7020: ldc_w         #284                // String abc
      7023: aastore
      7024: dup
>     7026: ldc_w         #286                // String def
      7029: aastore
      7030: dup
>     7032: ldc_w         #288                // String ghi
      7035: aastore
      7036: dup
>     7052: ldc_w         #375                // String blockWoodenDevice
      7055: lconst_1
      7056: bipush        6
>     7106: ldc_w         #375                // String blockWoodenDevice
      7109: lconst_1
      7110: bipush        6
>     7137: ldc_w         #362                // String blockCosmeticOpaque
      7140: lconst_1
      7141: iconst_2
>     7161: getstatic     #27                 // Field gregtech/api/enums/Mods.Gadomancy:Lgregtech/api/enums/Mods;
      7164: getfield      #31                 // Field gregtech/api/enums/Mods.ID:Ljava/lang/String;
>     7167: ldc_w         #466                // String ItemAuraCore
      7170: lconst_1
      7171: iconst_1
>     7197: ldc_w         #362                // String blockCosmeticOpaque
      7200: lconst_1
      7201: iconst_2
>     7227: ldc_w         #364                // String blockJar
      7230: lconst_1
      7231: iconst_0
>     7257: ldc_w         #468                // String blockTable
      7260: lconst_1
      7261: bipush        15
>     7288: ldc_w         #364                // String blockJar
      7291: lconst_1
      7292: iconst_0
>     7304: ldc_w         #461                // String GADOMANCY.ARCANE_PACKAGER
      7307: new           #175                // class thaumcraft/api/aspects/AspectList
      7310: dup
>     7314: ldc           #232                // String machina
      7316: invokestatic  #184                // Method 
thaumcraft/api/aspects/Aspect.getAspect:(Ljava/lang/String;)Lthaumcraft/api/aspects/Aspect;
      7319: bipush        18
>     7324: ldc_w         #356                // String aer
      7327: invokestatic  #184                // Method 
thaumcraft/api/aspects/Aspect.getAspect:(Ljava/lang/String;)Lthaumcraft/api/aspects/Aspect;
      7330: bipush        15
>     7335: ldc_w         #343                // String vacuos
      7338: invokestatic  #184                // Method 
thaumcraft/api/aspects/Aspect.getAspect:(Ljava/lang/String;)Lthaumcraft/api/aspects/Aspect;
      7341: bipush        12
>     7346: ldc           #192                // String praecantatio
      7348: invokestatic  #184                // Method 
thaumcraft/api/aspects/Aspect.getAspect:(Ljava/lang/String;)Lthaumcraft/api/aspects/Aspect;
      7351: bipush        9
>     7356: ldc_w         #455                // String potentia
      7359: invokestatic  #184                // Method 
thaumcraft/api/aspects/Aspect.getAspect:(Ljava/lang/String;)Lthaumcraft/api/aspects/Aspect;
      7362: bipush        6
>     7367: ldc           #212                // String arbor
      7369: invokestatic  #184                // Method 
thaumcraft/api/aspects/Aspect.getAspect:(Ljava/lang/String;)Lthaumcraft/api/aspects/Aspect;
      7372: iconst_3
>     7376: invokestatic  #220                // Method 
com/dreammaster/thaumcraft/TCHelper.setResearchAspects:(Ljava/lang/String;Lthaumcraft/api/aspects/AspectList;)V
>     7379: ldc_w         #461                // String GADOMANCY.ARCANE_PACKAGER
      7382: iconst_3
>     7383: invokestatic  #224                // Method 
com/dreammaster/thaumcraft/TCHelper.setResearchComplexity:(Ljava/lang/String;I)V
>     7386: ldc_w         #470                // String GADOMANCY.AURA_PYLON
>     7389: getstatic     #27                 // Field gregtech/api/enums/Mods.Gadomancy:Lgregtech/api/enums/Mods;
      7392: getfield      #31                 // Field gregtech/api/enums/Mods.ID:Ljava/lang/String;
>     7395: ldc           #165                // String BlockAuraPylon
      7397: lconst_1
      7398: iconst_0
>     7412: ldc           #198                // String ordo
      7414: invokestatic  #184                // Method 
thaumcraft/api/aspects/Aspect.getAspect:(Ljava/lang/String;)Lthaumcraft/api/aspects/Aspect;
      7417: bipush        100
>     7422: ldc_w         #360                // String aqua
      7425: invokestatic  #184                // Method 
thaumcraft/api/aspects/Aspect.getAspect:(Ljava/lang/String;)Lthaumcraft/api/aspects/Aspect;
      7428: bipush        100
>     7433: ldc_w         #356                // String aer
      7436: invokestatic  #184                // Method 
thaumcraft/api/aspects/Aspect.getAspect:(Ljava/lang/String;)Lthaumcraft/api/aspects/Aspect;
      7439: bipush        100
>     7444: ldc_w         #282                // String ignis
      7447: invokestatic  #184                // Method 
thaumcraft/api/aspects/Aspect.getAspect:(Ljava/lang/String;)Lthaumcraft/api/aspects/Aspect;
      7450: bipush        100
>     7462: ldc_w         #284                // String abc
      7465: aastore
      7466: dup
>     7468: ldc_w         #286                // String def
      7471: aastore
      7472: dup
>     7474: ldc_w         #288                // String ghi
      7477: aastore
      7478: dup
>     7494: ldc_w         #406                // String blockTube
      7497: lconst_1
      7498: bipush        6
>     7518: ldc_w         #472                // String stickIridium
      7521: aastore
      7522: dup
>     7540: ldc_w         #406                // String blockTube
      7543: lconst_1
      7544: bipush        6
>     7571: ldc           #204                // String blockMagicalLog
      7573: lconst_1
      7574: iconst_1
>     7600: ldc_w         #364                // String blockJar
      7603: lconst_1
      7604: iconst_0
>     7630: ldc           #204                // String blockMagicalLog
      7632: lconst_1
      7633: iconst_1
>     7659: ldc_w         #406                // String blockTube
      7662: lconst_1
      7663: bipush        6
>     7684: ldc_w         #472                // String stickIridium
      7687: aastore
      7688: dup
>     7706: ldc_w         #406                // String blockTube
      7709: lconst_1
      7710: bipush        6
>     7723: ldc_w         #470                // String GADOMANCY.AURA_PYLON
      7726: new           #175                // class thaumcraft/api/aspects/AspectList
      7729: dup
>     7733: ldc           #252                // String auram
      7735: invokestatic  #184                // Method 
thaumcraft/api/aspects/Aspect.getAspect:(Ljava/lang/String;)Lthaumcraft/api/aspects/Aspect;
      7738: bipush        18
>     7743: ldc           #198                // String ordo
      7745: invokestatic  #184                // Method 
thaumcraft/api/aspects/Aspect.getAspect:(Ljava/lang/String;)Lthaumcraft/api/aspects/Aspect;
      7748: bipush        15
>     7753: ldc           #192                // String praecantatio
      7755: invokestatic  #184                // Method 
thaumcraft/api/aspects/Aspect.getAspect:(Ljava/lang/String;)Lthaumcraft/api/aspects/Aspect;
      7758: bipush        12
>     7763: ldc           #232                // String machina
      7765: invokestatic  #184                // Method 
thaumcraft/api/aspects/Aspect.getAspect:(Ljava/lang/String;)Lthaumcraft/api/aspects/Aspect;
      7768: bipush        9
>     7773: ldc_w         #356                // String aer
      7776: invokestatic  #184                // Method 
thaumcraft/api/aspects/Aspect.getAspect:(Ljava/lang/String;)Lthaumcraft/api/aspects/Aspect;
      7779: bipush        6
>     7784: ldc_w         #282                // String ignis
      7787: invokestatic  #184                // Method 
thaumcraft/api/aspects/Aspect.getAspect:(Ljava/lang/String;)Lthaumcraft/api/aspects/Aspect;
      7790: iconst_3
>     7794: invokestatic  #220                // Method 
com/dreammaster/thaumcraft/TCHelper.setResearchAspects:(Ljava/lang/String;Lthaumcraft/api/aspects/AspectList;)V
>     7797: ldc_w         #470                // String GADOMANCY.AURA_PYLON
      7800: iconst_3
>     7801: invokestatic  #224                // Method 
com/dreammaster/thaumcraft/TCHelper.setResearchComplexity:(Ljava/lang/String;I)V
>     7804: ldc_w         #470                // String GADOMANCY.AURA_PYLON
>     7807: getstatic     #27                 // Field gregtech/api/enums/Mods.Gadomancy:Lgregtech/api/enums/Mods;
      7810: getfield      #31                 // Field gregtech/api/enums/Mods.ID:Ljava/lang/String;
>     7813: ldc           #165                // String BlockAuraPylon
      7815: lconst_1
      7816: iconst_1
>     7830: ldc           #198                // String ordo
      7832: invokestatic  #184                // Method 
thaumcraft/api/aspects/Aspect.getAspect:(Ljava/lang/String;)Lthaumcraft/api/aspects/Aspect;
      7835: bipush        125
>     7840: ldc_w         #356                // String aer
      7843: invokestatic  #184                // Method 
thaumcraft/api/aspects/Aspect.getAspect:(Ljava/lang/String;)Lthaumcraft/api/aspects/Aspect;
      7846: bipush        125
>     7851: ldc_w         #282                // String ignis
      7854: invokestatic  #184                // Method 
thaumcraft/api/aspects/Aspect.getAspect:(Ljava/lang/String;)Lthaumcraft/api/aspects/Aspect;
      7857: bipush        125
>     7869: ldc_w         #284                // String abc
      7872: aastore
      7873: dup
>     7875: ldc_w         #286                // String def
      7878: aastore
      7879: dup
>     7881: ldc_w         #288                // String ghi
      7884: aastore
      7885: dup
>     7895: ldc_w         #474                // String screwOsmiridium
      7898: aastore
      7899: dup
>     7916: ldc           #206                // String ItemResource
      7918: lconst_1
      7919: iconst_1
>     7939: ldc_w         #474                // String screwOsmiridium
      7942: aastore
      7943: dup
>     7961: ldc           #206                // String ItemResource
      7963: lconst_1
      7964: iconst_0
>     7984: getstatic     #27                 // Field gregtech/api/enums/Mods.Gadomancy:Lgregtech/api/enums/Mods;
      7987: getfield      #31                 // Field gregtech/api/enums/Mods.ID:Ljava/lang/String;
>     7990: ldc_w         #466                // String ItemAuraCore
      7993: lconst_1
      7994: iconst_2
>     8020: ldc           #206                // String ItemResource
      8022: lconst_1
      8023: iconst_0
>     8043: ldc_w         #472                // String stickIridium
      8046: aastore
      8047: dup
>     8059: getstatic     #27                 // Field gregtech/api/enums/Mods.Gadomancy:Lgregtech/api/enums/Mods;
      8062: getfield      #31                 // Field gregtech/api/enums/Mods.ID:Ljava/lang/String;
>     8065: ldc           #165                // String BlockAuraPylon
      8067: lconst_1
      8068: iconst_0
>     8088: ldc_w         #472                // String stickIridium
      8091: aastore
      8092: invokestatic  #304                // Method thaumcraft/api/ThaumcraftApi.addArcaneCraftingRecipe:(Ljava/lan
g/String;Lnet/minecraft/item/ItemStack;Lthaumcraft/api/aspects/AspectList;[Ljava/lang/Object;)Lthaumcraft/api/crafting/
ShapedArcaneRecipe;
>     8096: ldc_w         #476                // String GADOMANCY.KNOWLEDGE_BOOK
>     8099: getstatic     #27                 // Field gregtech/api/enums/Mods.Gadomancy:Lgregtech/api/enums/Mods;
      8102: getfield      #31                 // Field gregtech/api/enums/Mods.ID:Ljava/lang/String;
>     8105: ldc           #167                // String BlockKnowledgeBook
      8107: lconst_1
      8108: iconst_0
>     8122: ldc           #198                // String ordo
      8124: invokestatic  #184                // Method 
thaumcraft/api/aspects/Aspect.getAspect:(Ljava/lang/String;)Lthaumcraft/api/aspects/Aspect;
      8127: bipush        75
>     8132: ldc_w         #282                // String ignis
      8135: invokestatic  #184                // Method 
thaumcraft/api/aspects/Aspect.getAspect:(Ljava/lang/String;)Lthaumcraft/api/aspects/Aspect;
      8138: bipush        50
>     8143: ldc           #230                // String perditio
      8145: invokestatic  #184                // Method 
thaumcraft/api/aspects/Aspect.getAspect:(Ljava/lang/String;)Lthaumcraft/api/aspects/Aspect;
      8148: bipush        35
>     8153: ldc_w         #356                // String aer
      8156: invokestatic  #184                // Method 
thaumcraft/api/aspects/Aspect.getAspect:(Ljava/lang/String;)Lthaumcraft/api/aspects/Aspect;
      8159: bipush        35
>     8171: ldc_w         #284                // String abc
      8174: aastore
      8175: dup
>     8177: ldc_w         #286                // String def
      8180: aastore
      8181: dup
>     8183: ldc_w         #288                // String ghi
      8186: aastore
      8187: dup
>     8203: ldc_w         #478                // String ItemInkwell
      8206: lconst_1
      8207: iconst_0
>     8232: ldc_w         #480                // String ItemThaumonomicon
      8235: lconst_1
      8236: iconst_0
>     8262: ldc_w         #478                // String ItemInkwell
      8265: lconst_1
      8266: iconst_0
>     8292: ldc_w         #482                // String bookshelf
      8295: lconst_1
      8296: iconst_0
>     8316: getstatic     #27                 // Field gregtech/api/enums/Mods.Gadomancy:Lgregtech/api/enums/Mods;
      8319: getfield      #31                 // Field gregtech/api/enums/Mods.ID:Ljava/lang/String;
>     8322: ldc_w         #466                // String ItemAuraCore
      8325: lconst_1
      8326: iconst_5
>     8352: ldc_w         #482                // String bookshelf
      8355: lconst_1
      8356: iconst_0
>     8382: ldc_w         #377                // String blockMetalDevice
      8385: lconst_1
      8386: bipush        12
>     8413: ldc_w         #484                // String ItemGoggles
      8416: lconst_1
      8417: iconst_0
>     8443: ldc_w         #377                // String blockMetalDevice
      8446: lconst_1
      8447: bipush        12
>     8460: ldc_w         #476                // String GADOMANCY.KNOWLEDGE_BOOK
      8463: new           #175                // class thaumcraft/api/aspects/AspectList
      8466: dup
>     8470: ldc           #196                // String cognitio
      8472: invokestatic  #184                // Method 
thaumcraft/api/aspects/Aspect.getAspect:(Ljava/lang/String;)Lthaumcraft/api/aspects/Aspect;
      8475: bipush        24
>     8480: ldc           #198                // String ordo
      8482: invokestatic  #184                // Method 
thaumcraft/api/aspects/Aspect.getAspect:(Ljava/lang/String;)Lthaumcraft/api/aspects/Aspect;
      8485: bipush        21
>     8490: ldc           #192                // String praecantatio
      8492: invokestatic  #184                // Method 
thaumcraft/api/aspects/Aspect.getAspect:(Ljava/lang/String;)Lthaumcraft/api/aspects/Aspect;
      8495: bipush        18
>     8500: ldc           #232                // String machina
      8502: invokestatic  #184                // Method 
thaumcraft/api/aspects/Aspect.getAspect:(Ljava/lang/String;)Lthaumcraft/api/aspects/Aspect;
      8505: bipush        15
>     8510: ldc_w         #486                // String fabrico
      8513: invokestatic  #184                // Method 
thaumcraft/api/aspects/Aspect.getAspect:(Ljava/lang/String;)Lthaumcraft/api/aspects/Aspect;
      8516: bipush        12
>     8521: ldc           #190                // String motus
      8523: invokestatic  #184                // Method 
thaumcraft/api/aspects/Aspect.getAspect:(Ljava/lang/String;)Lthaumcraft/api/aspects/Aspect;
      8526: bipush        9
>     8531: ldc_w         #356                // String aer
      8534: invokestatic  #184                // Method 
thaumcraft/api/aspects/Aspect.getAspect:(Ljava/lang/String;)Lthaumcraft/api/aspects/Aspect;
      8537: bipush        6
>     8542: ldc_w         #335                // String lucrum
      8545: invokestatic  #184                // Method 
thaumcraft/api/aspects/Aspect.getAspect:(Ljava/lang/String;)Lthaumcraft/api/aspects/Aspect;
      8548: iconst_3
>     8552: invokestatic  #220                // Method 
com/dreammaster/thaumcraft/TCHelper.setResearchAspects:(Ljava/lang/String;Lthaumcraft/api/aspects/AspectList;)V
>     8555: ldc_w         #476                // String GADOMANCY.KNOWLEDGE_BOOK
      8558: iconst_3
>     8559: invokestatic  #224                // Method 
com/dreammaster/thaumcraft/TCHelper.setResearchComplexity:(Ljava/lang/String;I)V
>     8562: ldc_w         #476                // String GADOMANCY.KNOWLEDGE_BOOK
      8565: iconst_4
      8566: invokestatic  #489                // Method 
thaumcraft/api/ThaumcraftApi.addWarpToResearch:(Ljava/lang/String;I)V
>     8569: ldc_w         #491                // String GADOMANCY.ESSENTIA_COMPRESSOR
>     8572: getstatic     #27                 // Field gregtech/api/enums/Mods.Gadomancy:Lgregtech/api/enums/Mods;
      8575: getfield      #31                 // Field gregtech/api/enums/Mods.ID:Ljava/lang/String;
>     8578: ldc           #169                // String BlockEssentiaCompressor
      8580: lconst_1
      8581: iconst_0
>     8595: ldc_w         #356                // String aer
      8598: invokestatic  #184                // Method 
thaumcraft/api/aspects/Aspect.getAspect:(Ljava/lang/String;)Lthaumcraft/api/aspects/Aspect;
      8601: sipush        180
>     8607: ldc_w         #360                // String aqua
      8610: invokestatic  #184                // Method 
thaumcraft/api/aspects/Aspect.getAspect:(Ljava/lang/String;)Lthaumcraft/api/aspects/Aspect;
      8613: sipush        200
>     8619: ldc_w         #282                // String ignis
      8622: invokestatic  #184                // Method 
thaumcraft/api/aspects/Aspect.getAspect:(Ljava/lang/String;)Lthaumcraft/api/aspects/Aspect;
      8625: bipush        120
>     8630: ldc_w         #280                // String terra
      8633: invokestatic  #184                // Method 
thaumcraft/api/aspects/Aspect.getAspect:(Ljava/lang/String;)Lthaumcraft/api/aspects/Aspect;
      8636: bipush        100
>     8641: ldc           #230                // String perditio
      8643: invokestatic  #184                // Method 
thaumcraft/api/aspects/Aspect.getAspect:(Ljava/lang/String;)Lthaumcraft/api/aspects/Aspect;
      8646: sipush        140
>     8652: ldc           #198                // String ordo
      8654: invokestatic  #184                // Method 
thaumcraft/api/aspects/Aspect.getAspect:(Ljava/lang/String;)Lthaumcraft/api/aspects/Aspect;
      8657: sipush        160
>     8670: ldc_w         #284                // String abc
      8673: aastore
      8674: dup
>     8676: ldc_w         #286                // String def
      8679: aastore
      8680: dup
>     8682: ldc_w         #288                // String ghi
      8685: aastore
      8686: dup
>     8702: ldc_w         #406                // String blockTube
      8705: lconst_1
      8706: bipush        6
>     8732: ldc           #240                // String blockCrystal
      8734: lconst_1
      8735: iconst_4
>     8761: ldc_w         #406                // String blockTube
      8764: lconst_1
      8765: bipush        6
>     8792: ldc           #204                // String blockMagicalLog
      8794: lconst_1
      8795: iconst_0
>     8815: getstatic     #27                 // Field gregtech/api/enums/Mods.Gadomancy:Lgregtech/api/enums/Mods;
      8818: getfield      #31                 // Field gregtech/api/enums/Mods.ID:Ljava/lang/String;
>     8821: ldc_w         #493                // String ItemElement
      8824: lconst_1
      8825: iconst_0
>     8851: ldc           #204                // String blockMagicalLog
      8853: lconst_1
      8854: iconst_0
>     8880: ldc_w         #406                // String blockTube
      8883: lconst_1
      8884: bipush        6
>     8905: getstatic     #27                 // Field gregtech/api/enums/Mods.Gadomancy:Lgregtech/api/enums/Mods;
      8908: getfield      #31                 // Field gregtech/api/enums/Mods.ID:Ljava/lang/String;
>     8911: ldc_w         #466                // String ItemAuraCore
      8914: lconst_1
      8915: iconst_3
>     8941: ldc_w         #406                // String blockTube
      8944: lconst_1
      8945: bipush        6
>     8958: ldc_w         #491                // String GADOMANCY.ESSENTIA_COMPRESSOR
      8961: new           #175                // class thaumcraft/api/aspects/AspectList
      8964: dup
>     8968: ldc_w         #343                // String vacuos
      8971: invokestatic  #184                // Method 
thaumcraft/api/aspects/Aspect.getAspect:(Ljava/lang/String;)Lthaumcraft/api/aspects/Aspect;
      8974: bipush        21
>     8979: ldc           #230                // String perditio
      8981: invokestatic  #184                // Method 
thaumcraft/api/aspects/Aspect.getAspect:(Ljava/lang/String;)Lthaumcraft/api/aspects/Aspect;
      8984: bipush        18
>     8989: ldc           #232                // String machina
      8991: invokestatic  #184                // Method 
thaumcraft/api/aspects/Aspect.getAspect:(Ljava/lang/String;)Lthaumcraft/api/aspects/Aspect;
      8994: bipush        15
>     8999: ldc_w         #360                // String aqua
      9002: invokestatic  #184                // Method 
thaumcraft/api/aspects/Aspect.getAspect:(Ljava/lang/String;)Lthaumcraft/api/aspects/Aspect;
      9005: bipush        18
>     9010: ldc           #192                // String praecantatio
      9012: invokestatic  #184                // Method 
thaumcraft/api/aspects/Aspect.getAspect:(Ljava/lang/String;)Lthaumcraft/api/aspects/Aspect;
      9015: bipush        9
>     9020: ldc_w         #455                // String potentia
      9023: invokestatic  #184                // Method 
thaumcraft/api/aspects/Aspect.getAspect:(Ljava/lang/String;)Lthaumcraft/api/aspects/Aspect;
      9026: iconst_3
>     9030: invokestatic  #220                // Method 
com/dreammaster/thaumcraft/TCHelper.setResearchAspects:(Ljava/lang/String;Lthaumcraft/api/aspects/AspectList;)V
>     9033: ldc_w         #491                // String GADOMANCY.ESSENTIA_COMPRESSOR
      9036: iconst_3
>     9037: invokestatic  #224                // Method 
com/dreammaster/thaumcraft/TCHelper.setResearchComplexity:(Ljava/lang/String;I)V
>     9040: ldc_w         #495                // String GADOMANCY.AURA_EFFECTS
      9043: new           #175                // class thaumcraft/api/aspects/AspectList
      9046: dup
>     9050: ldc           #196                // String cognitio
      9052: invokestatic  #184                // Method 
thaumcraft/api/aspects/Aspect.getAspect:(Ljava/lang/String;)Lthaumcraft/api/aspects/Aspect;
      9055: bipush        27
>     9060: ldc           #252                // String auram
      9062: invokestatic  #184                // Method 
thaumcraft/api/aspects/Aspect.getAspect:(Ljava/lang/String;)Lthaumcraft/api/aspects/Aspect;
      9065: bipush        24
>     9070: ldc           #192                // String praecantatio
      9072: invokestatic  #184                // Method 
thaumcraft/api/aspects/Aspect.getAspect:(Ljava/lang/String;)Lthaumcraft/api/aspects/Aspect;
      9075: bipush        21
>     9080: ldc           #198                // String ordo
      9082: invokestatic  #184                // Method 
thaumcraft/api/aspects/Aspect.getAspect:(Ljava/lang/String;)Lthaumcraft/api/aspects/Aspect;
      9085: bipush        18
>     9090: ldc_w         #282                // String ignis
      9093: invokestatic  #184                // Method 
thaumcraft/api/aspects/Aspect.getAspect:(Ljava/lang/String;)Lthaumcraft/api/aspects/Aspect;
      9096: bipush        15
>     9101: ldc_w         #356                // String aer
      9104: invokestatic  #184                // Method 
thaumcraft/api/aspects/Aspect.getAspect:(Ljava/lang/String;)Lthaumcraft/api/aspects/Aspect;
      9107: bipush        12
>     9112: ldc_w         #360                // String aqua
      9115: invokestatic  #184                // Method 
thaumcraft/api/aspects/Aspect.getAspect:(Ljava/lang/String;)Lthaumcraft/api/aspects/Aspect;
      9118: bipush        9
>     9123: ldc_w         #280                // String terra
      9126: invokestatic  #184                // Method 
thaumcraft/api/aspects/Aspect.getAspect:(Ljava/lang/String;)Lthaumcraft/api/aspects/Aspect;
      9129: bipush        6
>     9134: ldc           #230                // String perditio
      9136: invokestatic  #184                // Method 
thaumcraft/api/aspects/Aspect.getAspect:(Ljava/lang/String;)Lthaumcraft/api/aspects/Aspect;
      9139: iconst_3
>     9143: invokestatic  #220                // Method 
com/dreammaster/thaumcraft/TCHelper.setResearchAspects:(Ljava/lang/String;Lthaumcraft/api/aspects/AspectList;)V
>     9146: ldc_w         #495                // String GADOMANCY.AURA_EFFECTS
      9149: iconst_4
>     9150: invokestatic  #224                // Method 
com/dreammaster/thaumcraft/TCHelper.setResearchComplexity:(Ljava/lang/String;I)V
>     9153: ldc           #173                // String GADOMANCY.GOLEMSILVERWOOD
      9155: invokestatic  #498                // Method 
com/dreammaster/thaumcraft/TCHelper.refreshResearchPages:(Ljava/lang/String;)V
>     9158: ldc           #226                // String GADOMANCY.GOLEMCOREBREAK
      9160: invokestatic  #498                // Method 
com/dreammaster/thaumcraft/TCHelper.refreshResearchPages:(Ljava/lang/String;)V
>     9163: ldc           #246                // String GADOMANCY.GOLEMCOREBODYGUARD
      9165: invokestatic  #498                // Method 
com/dreammaster/thaumcraft/TCHelper.refreshResearchPages:(Ljava/lang/String;)V
>     9168: ldc_w         #274                // String GADOMANCY.GOLEMRUNICSHIELD
      9171: invokestatic  #498                // Method 
com/dreammaster/thaumcraft/TCHelper.refreshResearchPages:(Ljava/lang/String;)V
>     9174: ldc_w         #276                // String GADOMANCY.ANCIENT_STONES
      9177: invokestatic  #498                // Method 
com/dreammaster/thaumcraft/TCHelper.refreshResearchPages:(Ljava/lang/String;)V
>     9180: ldc_w         #312                // String GADOMANCY.NODE_MANIPULATOR
      9183: invokestatic  #498                // Method 
com/dreammaster/thaumcraft/TCHelper.refreshResearchPages:(Ljava/lang/String;)V
>     9186: ldc_w         #345                // String GADOMANCY.INFUSIONCLAW
      9189: invokestatic  #498                // Method 
com/dreammaster/thaumcraft/TCHelper.refreshResearchPages:(Ljava/lang/String;)V
>     9192: ldc_w         #358                // String GADOMANCY.REMOTEJAR
      9195: invokestatic  #498                // Method 
com/dreammaster/thaumcraft/TCHelper.refreshResearchPages:(Ljava/lang/String;)V
>     9198: ldc_w         #368                // String GADOMANCY.ARCANEDROPPER
      9201: invokestatic  #498                // Method 
com/dreammaster/thaumcraft/TCHelper.refreshResearchPages:(Ljava/lang/String;)V
>     9204: ldc_w         #386                // String GADOMANCY.BLOCK_PROTECTOR
      9207: invokestatic  #498                // Method 
com/dreammaster/thaumcraft/TCHelper.refreshResearchPages:(Ljava/lang/String;)V
>     9210: ldc_w         #423                // String GADOMANCY.E_PORTAL_CREATOR
      9213: invokestatic  #498                // Method 
com/dreammaster/thaumcraft/TCHelper.refreshResearchPages:(Ljava/lang/String;)V
>     9216: ldc_w         #461                // String GADOMANCY.ARCANE_PACKAGER
      9219: invokestatic  #498                // Method 
com/dreammaster/thaumcraft/TCHelper.refreshResearchPages:(Ljava/lang/String;)V
>     9222: ldc_w         #470                // String GADOMANCY.AURA_PYLON
      9225: invokestatic  #498                // Method 
com/dreammaster/thaumcraft/TCHelper.refreshResearchPages:(Ljava/lang/String;)V
>     9228: ldc_w         #476                // String GADOMANCY.KNOWLEDGE_BOOK
      9231: invokestatic  #498                // Method 
com/dreammaster/thaumcraft/TCHelper.refreshResearchPages:(Ljava/lang/String;)V
>     9234: ldc_w         #491                // String GADOMANCY.ESSENTIA_COMPRESSOR
      9237: invokestatic  #498                // Method 
com/dreammaster/thaumcraft/TCHelper.refreshResearchPages:(Ljava/lang/String;)V
>     9240: ldc_w         #352                // String GADOMANCY.STICKYJAR
      9243: invokestatic  #498                // Method 
com/dreammaster/thaumcraft/TCHelper.refreshResearchPages:(Ljava/lang/String;)V
      9246: return
>           0    9247     0  this   Lcom/dreammaster/scripts/ScriptGadomancy;
  }


